[{"image": "./all_images/image_390.jpg", "codechart": "codecharts/code_chart_1581.jpg", "codes": ["Q31", "P63", "C25", "C45", "K82", "R48", "K97", "G17", "H42", "N16", "L45", "F37", "D47", "E79", "S43", "G72", "R36", "G98", "L87", "F18", "G95", "M98", "J57", "Q75", "A37", "U13", "U39", "Q27", "F53", "Z39", "W97", "F56", "U27", "U25", "B72", "Q67", "R82", "R78", "Y81", "W41", "D45", "L69", "U89", "W38", "K14", "B23", "R46", "U18", "W86", "M85", "W52", "C23", "W57", "X73", "B17", "W32", "Q97", "D95", "Z21", "S53", "Y98", "Z17", "F54", "M38", "R18", "K83", "W29", "V16", "V42", "J98", "C58", "D27", "Q58", "Z96", "M41", "V92", "C84", "K57", "S69", "R31", "M67", "Z34", "R47", "P62", "N69", "D89", "M54", "E48", "E42", "E52", "X31", "M28", "T58", "W51", "Q76", "Z79", "Z18", "N96", "W54", "F25", "Z16", "J76", "P86", "U71", "K54", "J74", "W18", "S92", "X63", "V95", "T31", "A12", "A89", "M59", "Q16", "D98", "J69", "G97", "Y86", "B85", "U34", "C68", "Q61", "L12", "U75", "L58", "N26", "M45", "X87", "A35", "Y46", "B51", "V45", "D53", "N52", "F79", "Q35", "G12", "X27", "N46", "V29", "C19", "Z51", "J67", "V25", "E43", "E56", "W46", "X48", "S71", "Q98", "W27", "U61", "M32", "H47", "R75", "X15", "U86", "S23", "R25", "N53", "Z45", "L52", "F91", "W16", "R52", "S97", "L84", "X93", "C63", "F26", "B73", "D75", "E27", "T34", "P34", "U41", "Y82", "A75", "H59", "S31", "V37", "C94", "J81", "D69", "F89", "V19", "K48", "V82", "B39", "A36", "E95", "E25", "G37", "E35", "S58", "Q82", "Q51", "P24", "D65", "J96", "S41", "M82", "M81", "K87", "P42", "V85", "V18", "X94", "N18", "V38", "V12", "V32", "C81", "E76", "L26", "K46", "A94", "X91", "V35", "Q19", "T59", "T56", "L62"], "flag": "real"}, {"image": "./all_images/image_364.jpg", "codechart": "codecharts/code_chart_1582.jpg", "codes": ["P21", "G89", "J42", "Z29", "G28", "L94", "K97", "B84", "B65", "A63", "V53", "Q12", "W43", "H74", "F37", "E79", "Y53", "J56", "N64", "T52", "X75", "U85", "D57", "Y51", "H54", "K74", "R65", "P58", "A93", "L79", "Q23", "F97", "Z23", "W67", "F65", "A56", "A19", "W74", "L63", "D97", "G54", "T23", "W41", "M21", "D45", "L69", "W38", "Y25", "K14", "K61", "J63", "N94", "W86", "A47", "T48", "Y38", "Y52", "C51", "G38", "L65", "P28", "G21", "H82", "G79", "W83", "Q79", "W29", "G47", "Q63", "U57", "D13", "N12", "P56", "E98", "Q86", "R31", "X43", "X84", "M67", "S18", "Q18", "X82", "J47", "M49", "F62", "K72", "Z28", "Z82", "D96", "N79", "Y75", "G73", "R24", "P86", "C12", "D15", "L31", "Z27", "R39", "G39", "B14", "L35", "A65", "X49", "Y36", "G32", "C57", "F71", "M59", "P54", "S39", "R28", "B85", "Q64", "X67", "R93", "D12", "V48", "E63", "X76", "Q39", "S14", "H97", "Y37", "T61", "M74", "B54", "X23", "P53", "Q21", "J15", "Q71", "V97", "J49", "M58", "Z51", "Z62", "M64", "Y27", "K62", "E72", "J54", "K41", "J67", "Y67", "W27", "R49", "P68", "L89", "B19", "E82", "T62", "C98", "R17", "N91", "Z15", "N51", "Y21", "A16", "Z67", "S51", "L19", "M65", "V61", "J34", "F74", "K26", "D75", "B36", "R37", "C47", "P61", "W69", "U84", "C78", "H71", "U41", "P17", "Q41", "S31", "W28", "J81", "G13", "M93", "A52", "V82", "U36", "X17", "V87", "L92", "C35", "Y13", "L17", "R63", "Q51", "N13", "S45", "Q91", "S41", "P52", "P42", "T87", "P85", "Q65", "B81", "W19", "P43", "V32", "R57", "A74", "U72", "M72", "H41", "L49", "W72", "M95", "F47", "F63", "V35", "B47", "R91", "E16", "R84", "L62"], "flag": "real"}, {"image": "./all_images/image_131.jpg", "codechart": "codecharts/code_chart_1583.jpg", "codes": ["U26", "J53", "Z29", "H15", "N49", "C61", "Z41", "A79", "M12", "J52", "T74", "N95", "L45", "U81", "Z26", "Z71", "E75", "W31", "A13", "Q62", "D58", "P97", "B89", "J56", "K91", "W68", "G63", "M98", "U85", "H56", "T18", "K16", "M51", "F64", "A82", "L37", "P36", "B98", "Y14", "F97", "E18", "Z23", "Z48", "W12", "B67", "Z74", "R83", "S67", "F56", "Y71", "U27", "S52", "R23", "D91", "B16", "L83", "L63", "J35", "V91", "R79", "J71", "Y42", "T64", "N23", "J45", "W86", "B95", "S12", "C23", "Y38", "J38", "D38", "D95", "B75", "T72", "P46", "Z17", "L65", "B92", "Y43", "W84", "N75", "W29", "Z24", "V42", "D27", "C48", "Y17", "V81", "T13", "T92", "V94", "V92", "L96", "T86", "B52", "Z12", "E26", "F28", "M49", "U83", "Z28", "E42", "Z79", "H65", "G81", "H37", "D78", "V14", "N96", "E36", "L76", "Z16", "P86", "C29", "H52", "R16", "L31", "U71", "T54", "Q92", "A95", "B14", "Q89", "R71", "X49", "X98", "K15", "C71", "A89", "T89", "Y97", "Y87", "C68", "Q61", "L12", "T37", "X76", "Z36", "L58", "F21", "N74", "Q17", "S14", "G43", "J15", "F59", "J67", "L93", "V25", "E56", "Y78", "M32", "F92", "R49", "P93", "L43", "V71", "U86", "N91", "E89", "Z63", "M56", "P31", "M87", "Z67", "R52", "L39", "K24", "L25", "K26", "G36", "D16", "X89", "C31", "H78", "R37", "R72", "K36", "V54", "B69", "U16", "J13", "K28", "R67", "P34", "M97", "K21", "T91", "X68", "F29", "E34", "X47", "T36", "U36", "B39", "N83", "A52", "A36", "R38", "E35", "D61", "B13", "P15", "A85", "P13", "X56", "V51", "S16", "Q91", "L85", "P42", "K87", "X94", "J73", "P43", "Z32", "Z47", "D62", "K46", "Q84", "Q36", "U69", "C73"], "flag": "real"}, {"image": "./all_images/image_197.jpg", "codechart": "codecharts/code_chart_1584.jpg", "codes": ["J53", "U97", "R53", "Q42", "J78", "N81", "M12", "U21", "P48", "N27", "G65", "A61", "B15", "Q96", "H74", "T49", "W34", "F73", "E79", "J27", "J82", "U95", "J43", "M94", "R41", "P32", "F51", "X34", "F18", "Y53", "R73", "G63", "X75", "A21", "X96", "Y51", "U39", "R65", "P58", "Z39", "S42", "H31", "L95", "Z74", "Y71", "K52", "U25", "K32", "L83", "D97", "B24", "T69", "T23", "W94", "S91", "D45", "M35", "U89", "Y25", "C43", "F67", "X85", "L48", "B95", "X46", "U64", "Y38", "C23", "Z53", "Y45", "W32", "H64", "N19", "J38", "D95", "C51", "Z21", "T72", "A25", "P28", "R18", "N75", "C58", "T12", "D74", "S48", "Q63", "P56", "K64", "H29", "S17", "L96", "C84", "N57", "X43", "G15", "J89", "H34", "Q78", "M62", "U83", "S72", "W92", "Q76", "H65", "W54", "H87", "R84", "A98", "Z65", "Y83", "G78", "G19", "H75", "L57", "L31", "R97", "D43", "H81", "D83", "X49", "G32", "A89", "N17", "V83", "K84", "H73", "S49", "X78", "Y97", "B85", "C68", "Y34", "D12", "R27", "P18", "G23", "B34", "Z38", "A53", "B54", "J32", "F79", "G12", "D64", "K78", "Y31", "H53", "S65", "W46", "Q48", "H47", "P68", "B19", "X64", "C65", "A41", "Z15", "F32", "N54", "K92", "T46", "Z67", "L25", "C63", "C92", "Y16", "T98", "R37", "G68", "W35", "N21", "V54", "F78", "J13", "R58", "M75", "S61", "W21", "M97", "H35", "K21", "P57", "H72", "E61", "A75", "U52", "H59", "L18", "N35", "V69", "G13", "Y92", "L92", "A57", "E95", "V87", "K17", "Y13", "B13", "U49", "N84", "U31", "Q94", "P24", "N13", "Y63", "R43", "Q57", "P85", "J64", "Z32", "D46", "B68", "D62", "E76", "M72", "U14", "F72", "X71", "G56", "U82", "T59", "V27"], "flag": "real"}, {"image": "./all_images/image_113.jpg", "codechart": "codecharts/code_chart_1585.jpg", "codes": ["X97", "N45", "E73", "N81", "W49", "T78", "N95", "Q12", "H26", "M46", "E93", "N87", "C56", "Q38", "P72", "M57", "C53", "A13", "D25", "M94", "A38", "M19", "D36", "X42", "S73", "B98", "T18", "M51", "U39", "Z23", "A67", "Z74", "R83", "W12", "F56", "U27", "T71", "X37", "H43", "L47", "L83", "E58", "L63", "Z75", "T69", "B24", "W41", "N89", "Y25", "A76", "J71", "N94", "Z61", "E29", "M53", "T48", "C24", "Y38", "F12", "K86", "D95", "T72", "Z21", "S15", "W84", "N75", "V42", "Q58", "D27", "E97", "C48", "E57", "D13", "G93", "R81", "T86", "R31", "B52", "U96", "C17", "G15", "F98", "J47", "W48", "Z28", "J17", "P67", "T94", "K12", "M68", "N96", "P38", "G45", "F19", "P86", "Y83", "J76", "S64", "C29", "C38", "L42", "H75", "G57", "F61", "T54", "J91", "B14", "V23", "D43", "J92", "M47", "F58", "M71", "G32", "C52", "F71", "F14", "J61", "Y96", "V83", "W23", "S81", "F83", "Y97", "T21", "L15", "F87", "R93", "X76", "E63", "N26", "W96", "J87", "S95", "N29", "P18", "G43", "G59", "Q29", "C95", "N46", "X27", "Z72", "P53", "F42", "N43", "M58", "Y31", "C74", "V63", "Y78", "M73", "E24", "R49", "Y64", "N92", "M96", "L43", "X64", "E39", "V71", "S87", "N91", "E89", "U53", "A41", "X15", "Y21", "N54", "Y74", "R76", "H27", "Y58", "S51", "K24", "C63", "C31", "B73", "H78", "U24", "V15", "W69", "T27", "W35", "P41", "L71", "Z87", "R58", "H71", "S47", "H72", "C54", "E34", "L18", "Y32", "R89", "P37", "K17", "X58", "R62", "B13", "T28", "R43", "C75", "V24", "L85", "M82", "W17", "Z54", "E54", "C81", "Z47", "V34", "X28", "L26", "N36", "C27", "B28", "Q84", "N39", "G56", "K13", "E41", "C97"], "flag": "real"}, {"image": "./sentinel_images/bucket1/sentinel_image_4.jpg", "codechart": "./codecharts/sentinel/sentineL_code_chart_4.jpg", "codes": "M78", "flag": "sentinel"}, {"image": "./all_images/image_263.jpg", "codechart": "codecharts/code_chart_1586.jpg", "codes": ["B76", "Z29", "U98", "R53", "A87", "L94", "N49", "F17", "V49", "U45", "M12", "L21", "U43", "G65", "T51", "A61", "H26", "Y57", "W43", "V93", "D47", "Z42", "U19", "A38", "P97", "N64", "R73", "M98", "H56", "X52", "D49", "D57", "A37", "U13", "V56", "F97", "B96", "W67", "W12", "L67", "G58", "K52", "F41", "A56", "X24", "N58", "J12", "E58", "Q52", "L63", "G54", "U89", "E83", "A76", "W95", "C79", "S24", "W57", "K49", "Y39", "Y45", "Q97", "E37", "V17", "F54", "U87", "R18", "K83", "M38", "J79", "G47", "X32", "K76", "V94", "L96", "T63", "Z83", "T86", "S13", "X84", "H36", "Q69", "M69", "Z34", "P96", "W76", "X82", "E26", "Q78", "N24", "Y49", "K72", "L41", "M26", "G81", "H87", "F25", "J76", "X39", "E49", "L42", "Y47", "K89", "K54", "C16", "A95", "D92", "R71", "U37", "X86", "X98", "W47", "G32", "Z92", "D98", "T89", "P75", "H73", "W79", "S49", "Y87", "R93", "P65", "L12", "E63", "Q39", "H69", "A35", "G43", "P87", "E85", "R87", "U35", "D51", "F42", "V97", "M84", "V39", "H53", "J54", "U46", "S65", "A59", "Y78", "E56", "Y28", "C59", "L24", "Y64", "C89", "P68", "Z13", "H85", "C98", "P71", "W87", "V71", "P73", "M15", "Z15", "N51", "D37", "K92", "U67", "J25", "P82", "M56", "F91", "W59", "M87", "D14", "G51", "Y16", "T19", "U24", "K36", "N21", "B69", "V54", "K28", "S61", "N14", "X68", "W91", "U91", "Z43", "E34", "A97", "E46", "U56", "D72", "K81", "Y41", "H32", "T42", "D69", "M93", "K47", "A36", "F93", "K17", "M25", "C35", "Q82", "S25", "C67", "P49", "P42", "W17", "S78", "Y68", "V62", "Z91", "P43", "X28", "B68", "H41", "K59", "W62", "W72", "B28", "N98", "T59", "H39"], "flag": "real"}, {"image": "./all_images/image_171.jpg", "codechart": "codecharts/code_chart_1587.jpg", "codes": ["P21", "E32", "U97", "Q37", "A87", "C61", "K97", "U45", "E28", "M12", "J31", "N37", "H42", "N16", "L45", "H58", "B15", "Y57", "W34", "F73", "G92", "D47", "T43", "E79", "A13", "Q62", "D25", "Q54", "X34", "E15", "G63", "X42", "A82", "V65", "Q85", "W61", "V84", "R74", "R21", "Q27", "Y69", "A17", "E18", "F56", "U27", "W58", "K32", "T71", "N58", "H43", "B16", "L83", "Z75", "R82", "R78", "N89", "U12", "W38", "J71", "E83", "U65", "W95", "V47", "P35", "J24", "T38", "L13", "W86", "F95", "Y39", "Y52", "Y45", "C83", "K79", "Z59", "D23", "V67", "S53", "Z86", "H82", "Y29", "G79", "V42", "J98", "R98", "S76", "D13", "W73", "J46", "V94", "E98", "S17", "N57", "K57", "B52", "X84", "Q69", "W76", "N86", "L72", "X82", "M62", "L41", "E48", "G71", "Z79", "A68", "N31", "P98", "X62", "V14", "G52", "B21", "U42", "J76", "R69", "L42", "B53", "W18", "S92", "B38", "A65", "U37", "P59", "S26", "E17", "L38", "M59", "E62", "W79", "G97", "Y12", "X26", "B85", "Q26", "L12", "P65", "U75", "W24", "N26", "Q39", "Q17", "N29", "J23", "U93", "Y37", "P87", "D53", "P84", "J32", "F42", "Q74", "J67", "Z62", "Y27", "J54", "M23", "E56", "T67", "E24", "Y64", "L89", "R45", "Y18", "T75", "E39", "B91", "X64", "W87", "S62", "P71", "P47", "F32", "M15", "U86", "R25", "Y74", "N54", "P39", "Z63", "H46", "T53", "T46", "Z67", "R52", "W16", "L39", "E96", "Z95", "T29", "C85", "D14", "T98", "H78", "N21", "J18", "W65", "F29", "A75", "E34", "F82", "T36", "N35", "T42", "M34", "V19", "E64", "E95", "S19", "D39", "R62", "K53", "W19", "G49", "X94", "Y76", "R57", "C81", "J37", "G53", "U52", "Q28", "C28", "U74"], "flag": "real"}, {"image": "./all_images/image_87.jpg", "codechart": "codecharts/code_chart_1588.jpg", "codes": ["Q31", "U26", "C25", "K82", "H15", "T81", "G28", "Z29", "U63", "E28", "A62", "N59", "B15", "H74", "N87", "T43", "C53", "M57", "J82", "R32", "G94", "V41", "Q54", "P32", "E19", "X75", "T85", "M51", "V65", "X18", "Z19", "U39", "A45", "L53", "W67", "H16", "M91", "Z74", "T68", "X79", "K52", "G84", "G34", "S59", "H43", "B16", "Q67", "A49", "M35", "U89", "A76", "J71", "W95", "F67", "L48", "B83", "J45", "T48", "D73", "L61", "W32", "F12", "Q97", "S79", "Y23", "B75", "V67", "S63", "G38", "Y29", "A15", "A26", "Q58", "D27", "C64", "W45", "J95", "U38", "D13", "S17", "E38", "C72", "S13", "D71", "J89", "H34", "S18", "H61", "F86", "N24", "F62", "Y62", "J17", "V36", "T58", "E59", "Q76", "M68", "U76", "P38", "B21", "Z64", "Z65", "Y35", "F13", "B53", "J83", "W18", "H45", "A78", "M71", "V95", "Z92", "G48", "J61", "F84", "P75", "T89", "J69", "X81", "Y86", "Y97", "M63", "Q61", "L12", "E63", "L29", "X87", "S14", "Y37", "D53", "M74", "M16", "A53", "X23", "N46", "Q74", "C19", "K78", "M64", "L93", "P16", "Q15", "S65", "Y78", "W71", "W98", "E14", "M32", "J59", "F69", "W42", "N92", "P68", "L24", "J36", "W53", "L43", "T62", "R75", "R68", "X65", "P73", "P47", "U67", "R96", "M56", "P31", "Y93", "R52", "Y65", "C85", "T29", "F74", "G24", "U47", "Z93", "B36", "C47", "R64", "T27", "N21", "T34", "E21", "R58", "R92", "M75", "S47", "H59", "L18", "C94", "D63", "H57", "H32", "G13", "F89", "K48", "A52", "L78", "L56", "D61", "R63", "K53", "T84", "N41", "C26", "C67", "C76", "P27", "E81", "J93", "B29", "A72", "H13", "U68", "X28", "D46", "P45", "H94", "U32", "B28", "V35", "N34", "C28"], "flag": "real"}, {"image": "./all_images/image_376.jpg", "codechart": "codecharts/code_chart_1589.jpg", "codes": ["S85", "J78", "A62", "M39", "U21", "D87", "L68", "H58", "E75", "Q62", "E19", "K91", "G95", "R73", "J57", "D94", "S73", "D17", "B98", "J85", "F97", "E18", "Y69", "M89", "R35", "R83", "S67", "K52", "X37", "D91", "J12", "A19", "W74", "C93", "E58", "Q67", "D97", "E87", "T69", "M21", "U12", "V91", "J71", "A76", "V47", "C79", "X61", "K61", "Z61", "W52", "B94", "W57", "Y38", "S63", "S93", "X21", "L65", "B92", "P28", "Y43", "K83", "F81", "A15", "X16", "V42", "V81", "U38", "S48", "W45", "T92", "Y61", "J46", "E98", "S17", "T63", "D76", "F86", "E26", "F28", "J47", "M24", "V36", "M28", "T58", "M68", "U76", "G52", "E36", "X19", "H75", "R16", "Q92", "U71", "A95", "Z27", "B14", "Q73", "S92", "V23", "M47", "J68", "T39", "F14", "J61", "Z69", "W14", "W23", "Z25", "K42", "E41", "Q64", "N48", "T97", "N72", "L12", "V48", "R93", "N74", "Q39", "M45", "T26", "U93", "P18", "B34", "C18", "D53", "N61", "Z72", "F42", "Q74", "X14", "Z62", "P16", "E43", "Q98", "E24", "H93", "L24", "F92", "N92", "R14", "B19", "R45", "C59", "H85", "T62", "S87", "U59", "B41", "H92", "B49", "S23", "W39", "B45", "Y74", "A16", "B25", "M87", "J62", "B64", "X93", "E96", "K24", "X89", "D75", "W69", "V76", "K36", "T34", "V54", "B69", "J13", "L71", "C78", "R92", "Y24", "P57", "W91", "S31", "C94", "U56", "T36", "J81", "Y32", "T42", "F89", "R56", "A52", "A57", "H76", "P37", "S19", "D21", "A84", "U51", "P15", "M78", "T47", "P42", "Y94", "S78", "E81", "H68", "P43", "A72", "C81", "E67", "E54", "E76", "M72", "S38", "X91", "L49", "P45", "C27", "G61", "K59", "B28", "W72", "A27", "C36", "G26", "E16", "U74"], "flag": "real"}, {"image": "./all_images/image_152.jpg", "codechart": "codecharts/code_chart_1590.jpg", "codes": ["C45", "G89", "T81", "G28", "F17", "M39", "J52", "T78", "X53", "N37", "L68", "T51", "F27", "M46", "E79", "Q38", "Z42", "G72", "Q62", "Q54", "A38", "B89", "P76", "R73", "X42", "U85", "Q75", "M51", "X18", "U39", "V56", "Q23", "Z39", "Z48", "Y59", "T96", "H28", "U25", "X35", "J26", "W74", "S86", "T69", "R78", "B24", "D45", "C43", "W95", "Y42", "J24", "R46", "E29", "A14", "M85", "N94", "X73", "L61", "F45", "F12", "J38", "Z21", "V17", "S21", "X83", "B92", "Y43", "G21", "K83", "W82", "V79", "A58", "A26", "K23", "Z96", "J95", "Q63", "S17", "C72", "R31", "C17", "V68", "G15", "Z12", "H61", "A64", "F28", "A39", "T17", "U83", "J17", "K58", "W92", "T57", "M28", "C37", "P67", "T94", "P98", "R24", "C13", "X39", "T54", "W85", "B53", "J74", "C16", "K39", "X86", "Y95", "A48", "T31", "L38", "Z94", "J61", "X95", "Z25", "L75", "W79", "Y87", "S94", "Y34", "D12", "F21", "L58", "L74", "Q39", "P29", "M74", "A46", "Q35", "N61", "Z72", "D51", "K25", "R26", "M84", "M58", "D64", "W71", "E91", "D41", "R19", "Q98", "E24", "U61", "M32", "H93", "M96", "T25", "B97", "H85", "T62", "P71", "R75", "S54", "F32", "M15", "W39", "R61", "K92", "U67", "J25", "U48", "R76", "F91", "B59", "W59", "Z95", "K26", "C92", "X89", "W69", "V76", "K36", "V54", "R67", "H71", "K21", "U41", "P17", "E61", "W65", "C54", "D24", "Z68", "E71", "K65", "Y32", "Q46", "B26", "F89", "E92", "F76", "D85", "D69", "M25", "L17", "A84", "A85", "C41", "Z98", "T47", "R43", "N13", "Q91", "P89", "C76", "C73", "S78", "X94", "E81", "V62", "C81", "R57", "D93", "A94", "L49", "F72", "S57", "Q84", "N98", "W56", "L62", "N56"], "flag": "real"}, {"image": "./sentinel_images/bucket1/sentinel_image_1.jpg", "codechart": "./codecharts/sentinel/sentineL_code_chart_1.jpg", "codes": "X21", "flag": "sentinel"}, {"image": "./all_images/image_190.jpg", "codechart": "codecharts/code_chart_1591.jpg", "codes": ["X97", "Z29", "N45", "Q37", "Q42", "K45", "H84", "K97", "B58", "F17", "A62", "M12", "F49", "X53", "N59", "N27", "D28", "T51", "H58", "H26", "T76", "N87", "E79", "P72", "Q62", "G98", "A38", "P97", "V73", "B89", "D36", "Q75", "H54", "Y51", "Q85", "Z19", "E53", "R65", "S96", "T96", "B67", "Z74", "R83", "X45", "S98", "Y71", "X79", "G58", "W58", "R23", "X35", "C93", "Q52", "B24", "F67", "B23", "T64", "K61", "Z53", "L34", "X73", "E51", "H64", "Q97", "V86", "T72", "S15", "P46", "A86", "A29", "Y15", "U87", "Y72", "Z24", "D74", "B79", "X32", "G93", "S17", "S13", "R31", "S69", "U96", "X43", "Y26", "M67", "J89", "H34", "P96", "Q18", "S83", "X69", "F28", "N63", "Z58", "M28", "W51", "N79", "N31", "K71", "U94", "Z16", "Z65", "P64", "X39", "D15", "E49", "M27", "Q92", "W36", "K54", "J83", "W18", "B53", "K18", "K39", "V31", "X98", "K98", "H12", "S26", "E17", "C52", "N76", "Z94", "U58", "C91", "A73", "W23", "Z69", "P54", "X78", "Y87", "F96", "C68", "Q61", "U73", "S95", "P18", "P29", "G59", "V45", "E85", "Q95", "J32", "Y48", "K25", "B82", "J49", "M58", "A23", "F57", "K62", "H53", "P16", "U46", "K41", "A59", "M73", "V96", "N68", "J36", "Q98", "B32", "Y18", "K63", "N91", "P47", "M15", "N51", "R96", "M56", "M87", "D42", "J62", "Y58", "T15", "T29", "F26", "E12", "R37", "C47", "V15", "T34", "U16", "U62", "M14", "H19", "P34", "H72", "G67", "W64", "C94", "U56", "E71", "U78", "K65", "Y92", "U36", "H76", "D39", "L56", "Z31", "Z49", "N84", "Y63", "T47", "Q91", "V18", "E54", "P43", "S89", "Z91", "R57", "Z32", "X28", "A74", "U72", "D46", "B28", "G56", "S28", "D67", "V27"], "flag": "real"}, {"image": "./all_images/image_335.jpg", "codechart": "codecharts/code_chart_1592.jpg", "codes": ["P63", "B35", "K29", "S85", "G28", "P69", "H51", "E73", "V49", "B65", "U21", "F49", "K94", "T51", "T93", "H58", "F27", "A96", "L59", "S43", "U95", "J43", "F51", "F18", "B87", "E15", "C97", "B98", "K74", "M83", "E53", "F43", "R21", "Z39", "E18", "M91", "L95", "V75", "F65", "S67", "A56", "S59", "A19", "L47", "D97", "G54", "F68", "D31", "W41", "D48", "R79", "U89", "Y25", "C43", "C79", "P35", "R46", "W57", "Q45", "V43", "K79", "Z59", "C51", "Y15", "X83", "U87", "F54", "Y43", "W29", "J79", "X16", "D74", "G47", "X32", "G16", "Q63", "T13", "P56", "X51", "B63", "E84", "S17", "R81", "B71", "T63", "M17", "D71", "C21", "F62", "T65", "M24", "U83", "T16", "T82", "Y75", "T73", "Z37", "K71", "W54", "G14", "X19", "K35", "J74", "L91", "G39", "Q89", "Q73", "D92", "A18", "H81", "A65", "A78", "D43", "M71", "N76", "G32", "C71", "C57", "T31", "M59", "W23", "K84", "L75", "Y12", "S49", "F85", "R85", "X67", "Q59", "U75", "Z36", "A83", "F21", "N74", "Q56", "Q17", "F39", "V59", "U93", "G23", "A35", "F46", "B51", "P87", "M16", "D53", "P84", "C46", "N46", "V97", "L86", "W26", "M58", "K62", "Y27", "V25", "B46", "X48", "W37", "R15", "C89", "U29", "R45", "R68", "X65", "P73", "B45", "K43", "N53", "B25", "R96", "L52", "R52", "W16", "R94", "T24", "L25", "Y16", "D75", "X89", "D35", "U16", "R67", "S37", "Y82", "S47", "C54", "N35", "Y92", "Q47", "A57", "Z73", "R95", "R38", "R89", "P92", "M25", "D21", "B37", "R62", "Q51", "U49", "Z98", "Y63", "C67", "H18", "P49", "M82", "L85", "G49", "V38", "E86", "U68", "D62", "U32", "E74", "N82", "L27", "B28", "B31", "G53", "N39", "T59", "E16"], "flag": "real"}, {"image": "./all_images/image_194.jpg", "codechart": "codecharts/code_chart_1593.jpg", "codes": ["P63", "P21", "E32", "B76", "U97", "M42", "G64", "A62", "M39", "G74", "Q43", "G65", "L45", "Q12", "S46", "M46", "E93", "C56", "E75", "Z71", "S43", "R36", "G94", "V72", "G63", "H56", "X52", "X18", "L97", "A17", "R35", "H16", "Y59", "V75", "Y71", "G25", "G58", "U25", "K52", "B16", "T69", "H83", "J35", "M35", "V91", "R79", "E83", "V47", "W95", "B23", "U18", "L48", "R46", "G82", "C23", "J38", "V17", "T72", "S15", "C39", "Z17", "Z86", "G79", "A58", "V16", "B79", "J29", "D13", "J86", "E98", "Y54", "Q93", "E38", "B52", "D76", "Q69", "R47", "N15", "F28", "N69", "T65", "Z28", "T57", "C37", "P67", "Y75", "N31", "T73", "M68", "K71", "U76", "G14", "G73", "Z16", "C38", "D15", "T54", "L57", "K89", "C16", "R54", "W18", "U71", "K18", "A34", "A65", "J92", "N71", "X63", "V95", "Y36", "H67", "P75", "Z25", "T95", "Y12", "H73", "H48", "Q61", "W24", "L58", "R51", "X38", "F21", "B93", "S95", "M45", "J23", "U93", "P29", "Y46", "M16", "A53", "C46", "K25", "L86", "M84", "X14", "A23", "F57", "P83", "V25", "J54", "E56", "W13", "W71", "M73", "V96", "S71", "B32", "Q98", "R15", "F92", "W42", "M96", "E82", "Z13", "H85", "X64", "Q83", "B41", "T75", "P47", "K43", "R25", "N54", "Z63", "H46", "R96", "G36", "K24", "M52", "L46", "R64", "W35", "K36", "S61", "P57", "F34", "Y82", "C54", "W91", "E47", "E46", "E71", "K65", "Y32", "G13", "F89", "M93", "A36", "S19", "R38", "P37", "K38", "D21", "Z49", "A84", "Q53", "Q51", "F23", "T84", "T28", "S45", "P49", "V18", "Y68", "H25", "V62", "Z54", "J93", "V38", "J73", "J37", "P45", "S57", "G61", "F63", "N65", "Q19", "E41", "T56", "C73", "U74"], "flag": "real"}, {"image": "./all_images/image_286.jpg", "codechart": "codecharts/code_chart_1594.jpg", "codes": ["B76", "E32", "R53", "G64", "A62", "M39", "S46", "Y57", "H74", "D47", "G96", "Q38", "C53", "F18", "B87", "R73", "M98", "F15", "W56", "A21", "D57", "Q85", "F97", "F43", "L95", "H16", "B67", "X45", "S67", "H89", "S52", "G84", "T71", "D91", "J26", "W15", "A19", "S86", "R78", "H83", "A49", "U89", "K14", "W95", "X47", "T64", "U18", "F31", "T48", "T14", "C24", "W52", "Z59", "C39", "X21", "U28", "G91", "A58", "Q58", "J95", "R98", "T13", "S48", "J46", "A54", "E98", "Y61", "E57", "B63", "X84", "D71", "H36", "Z34", "F86", "J84", "L72", "Q78", "F28", "T17", "K72", "W48", "M24", "K51", "B57", "X31", "W92", "T57", "M28", "T58", "B86", "W54", "G73", "Z65", "S64", "H75", "Y47", "B53", "H23", "J91", "X41", "B38", "V21", "U54", "H12", "Z92", "Q49", "C91", "Q16", "J69", "L75", "H48", "Q24", "F85", "R85", "Y84", "N72", "T37", "W24", "G86", "R27", "W96", "S82", "J23", "T26", "V57", "T61", "R86", "J28", "M16", "A53", "G41", "Z38", "J32", "A46", "L86", "V29", "J49", "M58", "K78", "F57", "Y27", "J54", "E72", "M31", "B46", "W98", "E91", "Y28", "W37", "F69", "W53", "Y64", "L24", "V74", "R14", "N68", "U61", "Y18", "M32", "C98", "P71", "X64", "A51", "G42", "S62", "H96", "A41", "W39", "N51", "D56", "Z63", "U48", "D42", "Y93", "L19", "V61", "L18", "L25", "C63", "R72", "E12", "R37", "C47", "E27", "V54", "E21", "K28", "S61", "M75", "R67", "C54", "F29", "W91", "A75", "U78", "L82", "C94", "D72", "K65", "H57", "K81", "N35", "F89", "E92", "E64", "K38", "Y13", "X56", "S16", "Z98", "M78", "Q57", "Q91", "V85", "D29", "E81", "V12", "V32", "S38", "Q84", "G56", "A27", "U82", "U74"], "flag": "real"}, {"image": "./all_images/image_26.jpg", "codechart": "codecharts/code_chart_1595.jpg", "codes": ["P63", "M42", "S85", "Q42", "C61", "E28", "J52", "B65", "N27", "N59", "D87", "E93", "W43", "F73", "E79", "G92", "Z71", "M57", "U23", "E19", "Y53", "B56", "V72", "N64", "D36", "X42", "D94", "T18", "Q75", "M51", "F64", "X18", "U13", "U17", "L53", "R21", "F53", "T96", "Y59", "S67", "F56", "H89", "A56", "D91", "H43", "L83", "S86", "G54", "V52", "R79", "Y25", "V47", "E23", "F67", "B23", "J24", "K61", "L13", "W86", "Z53", "V43", "U92", "B75", "C51", "S15", "S21", "S63", "K67", "F54", "P28", "G21", "R18", "Y29", "N75", "G91", "Z24", "X16", "Y72", "K23", "D27", "G16", "E57", "J46", "B63", "V94", "H29", "R81", "Z83", "B71", "N57", "X84", "B52", "C72", "C21", "N15", "A64", "Q78", "F62", "U83", "N79", "E59", "U76", "P38", "N93", "D15", "W75", "G19", "R16", "H75", "C16", "H23", "Q73", "B61", "X41", "V64", "R97", "X86", "M61", "L38", "A12", "A73", "L51", "S39", "Z25", "J69", "W79", "G97", "F83", "N48", "T97", "X76", "E63", "G86", "Q17", "G59", "Z38", "E85", "L81", "C46", "G12", "R26", "C28", "L86", "V29", "M58", "A23", "D64", "Z62", "Y31", "E43", "E56", "M31", "W25", "S71", "J36", "C59", "W42", "W53", "U29", "M76", "G42", "B91", "K63", "S62", "H92", "N91", "M15", "F52", "S68", "Z63", "Y93", "R52", "V61", "L84", "X93", "U47", "Z93", "E12", "R72", "U24", "P61", "K36", "D35", "L32", "M14", "J94", "Y24", "H71", "P17", "H72", "Q41", "S31", "Y92", "M93", "L92", "A57", "R95", "E35", "M25", "R62", "U51", "A69", "P13", "T84", "R43", "C75", "C67", "N13", "C73", "Y94", "Q87", "S89", "V98", "J75", "E67", "L26", "F72", "S57", "N82", "V35", "N39", "N98", "S74", "H39"], "flag": "real"}, {"image": "./sentinel_images/bucket1/sentinel_image_3.jpg", "codechart": "./codecharts/sentinel/sentineL_code_chart_3.jpg", "codes": "K13", "flag": "sentinel"}, {"image": "./all_images/image_396.jpg", "codechart": "codecharts/code_chart_1596.jpg", "codes": ["C45", "E32", "K82", "Q37", "E69", "A63", "N95", "A61", "G31", "Q12", "V53", "S46", "Y57", "J27", "N25", "K19", "E75", "J82", "U95", "U19", "L87", "M19", "B87", "B56", "D36", "T52", "X96", "T85", "B27", "B98", "L98", "V65", "A37", "U17", "J85", "A45", "V84", "R21", "H16", "Z48", "W12", "G25", "H89", "S52", "X37", "W74", "E58", "V28", "R82", "N89", "U12", "A49", "M35", "A32", "U89", "D68", "N94", "A47", "T48", "W52", "Z53", "X73", "Y52", "Y45", "S79", "S63", "K67", "X21", "W84", "U87", "Y43", "K83", "F81", "H82", "W29", "Q79", "J16", "J29", "G16", "X32", "E97", "M41", "S48", "V94", "Y54", "T86", "C72", "R31", "N57", "L54", "P96", "C21", "H61", "M49", "E48", "J17", "K51", "E52", "V36", "T58", "Z79", "G14", "G45", "X39", "H95", "P23", "L42", "R16", "F61", "B53", "R54", "J83", "G39", "Q89", "K69", "A78", "D43", "V31", "D81", "Q49", "H67", "X54", "Z84", "Y87", "Q64", "L28", "C68", "T97", "E63", "K75", "N62", "N74", "Q39", "C87", "J87", "Q17", "X87", "H69", "G43", "T61", "C18", "N52", "B54", "L81", "F79", "K25", "M84", "M58", "D64", "J14", "Q15", "M31", "V63", "A59", "D41", "E24", "W27", "W42", "H85", "B41", "C65", "P47", "Z15", "N53", "U67", "T53", "T46", "Y58", "L39", "L84", "G36", "D16", "D75", "C47", "W69", "R64", "N21", "T34", "E21", "P34", "G87", "Z81", "U91", "E34", "U78", "K65", "X17", "Z73", "R95", "E25", "P37", "L56", "Z31", "P92", "R63", "E95", "P15", "Q94", "P89", "N13", "H18", "S41", "P49", "L85", "K87", "V85", "D29", "W19", "G49", "B74", "V12", "C81", "R57", "X92", "U68", "J75", "U72", "H41", "B31", "B62", "M13", "U52", "J31", "C73"], "flag": "real"}, {"image": "./all_images/image_121.jpg", "codechart": "codecharts/code_chart_1597.jpg", "codes": ["Q37", "R48", "C61", "E73", "J39", "M39", "B65", "L21", "K94", "N59", "T51", "H26", "W34", "G92", "G94", "W31", "Q62", "F51", "P97", "R41", "X75", "H56", "A82", "T18", "Q81", "J85", "V56", "S96", "R65", "Q25", "R74", "F53", "Y71", "A56", "U25", "R23", "B16", "L83", "Q67", "Q52", "W74", "E87", "F68", "H21", "D48", "M35", "Z76", "E83", "S36", "P74", "T64", "P35", "G82", "N47", "A47", "W86", "B95", "U64", "X46", "Y38", "N97", "Y56", "E37", "C51", "V86", "Q28", "G38", "A29", "A25", "F54", "U87", "H82", "J79", "J29", "J95", "U57", "W73", "K76", "J46", "T92", "V94", "V92", "R81", "N57", "K57", "J65", "Z12", "A42", "N63", "M62", "M24", "Z46", "U83", "Y62", "E48", "M68", "G73", "U42", "F75", "R24", "X19", "P64", "Y83", "G19", "H75", "S75", "Q92", "C16", "A95", "B61", "X41", "R71", "F58", "D83", "N71", "Y95", "X98", "X49", "K98", "S26", "Z92", "E17", "Q49", "C91", "Z69", "X95", "T95", "K42", "N48", "R85", "C68", "Q61", "P65", "T37", "V48", "Q56", "J87", "U93", "H69", "A35", "G43", "Z38", "R26", "V39", "Q74", "V29", "K78", "Y27", "M23", "G27", "G75", "Y28", "R19", "W42", "M76", "X64", "C98", "K63", "U86", "B49", "R61", "Y74", "D56", "Z45", "U67", "P82", "B25", "P39", "D14", "T24", "T29", "Z95", "C63", "Y16", "M52", "C47", "W35", "V54", "M14", "R92", "Z81", "H35", "W65", "W91", "U52", "Q41", "G67", "U91", "D24", "Q13", "C94", "H32", "D85", "C35", "X58", "Q72", "X56", "K53", "N41", "D65", "S41", "L85", "V58", "W17", "P27", "V38", "J93", "D59", "H13", "C81", "Y76", "E76", "J58", "J37", "U14", "F72", "K59", "W72", "M95", "V35", "B62", "U82", "N73", "S74"], "flag": "real"}, {"image": "./sentinel_images/bucket1/sentinel_image_2.jpg", "codechart": "./codecharts/sentinel/sentineL_code_chart_2.jpg", "codes": "L92", "flag": "sentinel"}, {"image": "./all_images/image_391.jpg", "codechart": "codecharts/code_chart_1598.jpg", "codes": ["E32", "N45", "K82", "V49", "B65", "C96", "K94", "A63", "D87", "A61", "Z52", "W43", "J27", "N87", "K19", "D47", "Z26", "G96", "M57", "X34", "V72", "G63", "D57", "A37", "Y14", "A17", "Z23", "W67", "H28", "R21", "Y85", "V75", "S67", "G34", "A56", "J26", "L63", "R82", "M21", "Y81", "W41", "W94", "J35", "U12", "W38", "V47", "M13", "F67", "B23", "P35", "L48", "D68", "T48", "T14", "F45", "Y79", "Y15", "S53", "S21", "A25", "M38", "H82", "Y29", "J79", "V16", "Z24", "V81", "Z96", "C64", "S76", "D13", "P56", "W73", "Z78", "E98", "G16", "A54", "T63", "B71", "X84", "X43", "H36", "J65", "J89", "M67", "X69", "L72", "Q68", "G35", "E31", "L41", "D89", "J17", "M28", "Z79", "Q76", "V13", "H65", "Z18", "N96", "P38", "M48", "X19", "Z16", "C13", "R69", "H95", "S64", "W85", "J74", "B14", "Q89", "S92", "F58", "P59", "A78", "M71", "A65", "S26", "C71", "C52", "P19", "Y96", "D98", "S81", "W79", "E41", "G83", "R85", "L15", "X38", "M45", "V59", "H69", "X87", "A53", "N52", "B54", "C46", "K93", "N43", "W26", "M58", "M23", "J54", "Y78", "E91", "V96", "R15", "Y64", "P81", "V74", "M96", "C89", "U61", "Z13", "T62", "C59", "N91", "S54", "B49", "F32", "A41", "D37", "D56", "H46", "P31", "Z67", "S51", "L84", "Z95", "G36", "F26", "B73", "U47", "C31", "U84", "U62", "C78", "R58", "Z81", "K21", "W64", "E46", "D63", "N35", "H57", "K81", "Y41", "K47", "A57", "R95", "Z73", "S19", "P37", "E65", "Q53", "S25", "K53", "T84", "P89", "R43", "J96", "L85", "W19", "Q65", "K34", "V62", "B29", "Z54", "S89", "V98", "A94", "L27", "W72", "G53", "V35", "N28", "Q36", "B47", "D67", "B68", "R84", "L62"], "flag": "real"}, {"image": "./all_images/image_404.jpg", "codechart": "codecharts/code_chart_1599.jpg", "codes": ["P63", "U97", "Q42", "E69", "B47", "U21", "K94", "T74", "G65", "T51", "G31", "G76", "U81", "M46", "W34", "J27", "F73", "K19", "E79", "N25", "M57", "L59", "J51", "E19", "V72", "V26", "M98", "X72", "W56", "L97", "Z19", "V56", "W61", "M91", "R83", "S67", "Y71", "G25", "K52", "D91", "X35", "W15", "C93", "D97", "M21", "U12", "C43", "B23", "M53", "Y38", "L61", "K49", "F45", "H64", "V43", "E51", "Y56", "K79", "D23", "V17", "V67", "C39", "G38", "F54", "Z86", "G21", "Y72", "Z24", "T12", "B79", "G47", "Q63", "T13", "S76", "W73", "U69", "H29", "E98", "Y54", "R81", "P95", "H36", "P96", "X25", "N86", "F28", "M62", "T17", "Z58", "L41", "T16", "J17", "X31", "Q76", "G81", "P51", "G14", "T45", "A98", "L76", "R69", "P23", "H52", "Y35", "C29", "L57", "A92", "K54", "Z27", "R54", "H49", "R97", "V95", "S26", "Z92", "G48", "C57", "F14", "L51", "W23", "S39", "Z25", "J69", "N48", "R42", "R93", "R51", "C87", "X87", "Y37", "G43", "Z38", "N43", "Q74", "M84", "F38", "Z51", "C74", "P83", "J14", "V63", "G75", "W46", "W25", "X48", "E91", "D41", "L14", "Y78", "W53", "L24", "C89", "P68", "X59", "Y18", "U59", "B91", "X65", "P47", "R29", "N51", "S23", "F36", "Y74", "F24", "Z45", "P82", "P31", "D42", "Y58", "D14", "T46", "L84", "T15", "G36", "F74", "D16", "G51", "C31", "Y16", "W35", "D35", "E21", "C78", "S61", "S37", "Y82", "N42", "Q41", "U91", "C69", "W64", "E46", "L23", "A52", "S19", "G37", "Z31", "Z49", "U51", "A69", "V51", "U31", "R43", "C67", "G85", "G49", "Y68", "N18", "Q87", "E81", "N78", "V98", "X92", "D54", "K46", "P45", "K59", "N36", "G53", "N39", "Q19", "N34", "R91"], "flag": "real"}, {"image": "./all_images/image_133.jpg", "codechart": "codecharts/code_chart_1600.jpg", "codes": ["P63", "L36", "X97", "K82", "U98", "B58", "X29", "J39", "B47", "M12", "W49", "B84", "P48", "N37", "B42", "V53", "H58", "Q96", "Z52", "F73", "E79", "P25", "E75", "U19", "G98", "D25", "X34", "J21", "Y53", "G63", "A82", "T18", "M51", "V65", "U39", "Q25", "Y14", "H28", "Z48", "A67", "Z74", "R83", "Y71", "A56", "S52", "X35", "S35", "J12", "A19", "W74", "F68", "L69", "B23", "U18", "B83", "B95", "M53", "F95", "X46", "Y38", "L61", "N97", "W32", "Y23", "P46", "S93", "N75", "G21", "Q34", "K23", "D27", "M41", "X51", "V94", "V92", "B71", "H34", "A42", "Z58", "Z28", "K51", "Z56", "M28", "G71", "Y75", "V13", "W54", "D78", "J76", "N93", "S64", "A91", "D15", "C29", "G57", "H75", "U71", "W36", "B53", "R54", "C82", "R71", "D26", "K39", "H49", "A65", "Y36", "U54", "M61", "J61", "A12", "A89", "Z69", "H86", "T89", "D98", "Z25", "W79", "Y12", "S94", "N48", "Y84", "Q26", "V48", "D12", "Q39", "V59", "G23", "B34", "M74", "R86", "Q95", "L81", "Y48", "V97", "A23", "J14", "J54", "S65", "Y78", "B32", "F69", "H93", "M76", "Y18", "E39", "X15", "V71", "Q83", "X64", "H96", "A41", "Z15", "S23", "W39", "Y21", "U67", "R76", "E45", "T53", "L19", "X93", "T15", "Z95", "T24", "F74", "C31", "L46", "C47", "P61", "F78", "S61", "W21", "C34", "S37", "P57", "E61", "Z43", "F82", "E46", "U56", "E71", "K81", "V69", "T42", "Q46", "D69", "L23", "K47", "X17", "A57", "V19", "P37", "E35", "P92", "X58", "Q72", "U51", "Q51", "C62", "F23", "C41", "Q94", "T28", "Y63", "S45", "M82", "W17", "S78", "V18", "H68", "D59", "X28", "J58", "P45", "H94", "W62", "W72", "B28", "N39", "A27", "N34", "C97", "N56"], "flag": "real"}]