[{"image": "image_180.jpg", "codechart": "codecharts/code_chart_241.jpg", "codes": ["P76", "B95", "D39", "P16", "A16", "N41", "E30", "A54", "W76", "Q39", "V46", "J94", "A87", "E85", "T41", "B93", "U76", "G56", "A81", "H24", "C84", "M72", "L34", "P20", "X91", "W35", "W71", "Q87", "S90", "G69", "X67", "P65", "U90", "M38", "U17", "V34", "F69", "R41", "J65", "A43", "N75", "A78", "D93", "M62", "H16", "N40", "L36", "D32", "J10", "T67", "P38", "U61", "R32", "Y45", "X94", "A41", "W24", "L50", "D69", "Q30", "W87", "R98", "L37", "T25", "E48", "R82", "M29", "H47", "J57", "J67", "V83", "N23", "W42", "A25", "R91", "Y49", "K87", "K20", "N32", "W70", "E31", "W75", "B48", "H92", "L97", "J87", "L10", "A14", "Z53", "Z13", "H83", "H57", "X20", "G82", "A96", "Y67", "C28", "T57", "C19", "E60", "X18", "N14", "S13", "R27", "M75", "C59", "V72", "N87", "A85", "A47", "U72", "X62", "H58", "W96", "C72", "F42", "S54", "X28", "F74", "B90", "X81", "C17", "Y94", "W98", "R43", "F34", "K47", "H95", "H61", "K24", "N60", "S98", "Q92", "N97", "G85", "T64", "G32", "Y69", "L41", "S47", "E15", "W54", "Y29", "H23", "D84", "R61", "N34", "T85", "B15", "X48", "W36", "S78", "Q23", "J95", "H73", "W79", "B13", "Q82", "N74", "V56", "T29", "X38", "R42", "H81", "B60", "K17", "D45", "A62", "S60", "U85", "X84", "M56", "X80", "R39", "P13", "Y64", "C46", "H20", "E83", "F27", "N17", "C97", "Y51", "Y16", "L96", "Q43", "X60", "W78", "D86", "P67", "C15", "K97", "D96", "W26", "G15", "V30", "P84", "B14", "G52", "S18", "T90", "T70", "E90", "X34", "E67", "B92", "B35", "G35", "J61", "D43", "V47", "L82", "A63", "N58", "Q59", "M97", "Z69", "X13", "G42", "W84", "F73", "C94", "B45", "E36", "C83", "D59", "V48", "U16", "C60", "X86", "E46", "P26", "L58", "C73", "T46", "F60", "P43", "V92", "P19", "P53", "A36", "Q45", "L30", "L29", "A53", "Z24", "B84", "C53", "D78", "W68", "Z12", "T32", "J52", "N81", "Q50", "M60", "M59", "V12", "P49", "K36", "D10", "P79", "S46", "G51", "N12", "P45", "C79", "M61", "Q96", "L24", "G17", "R71", "P58", "J48", "S71", "L87", "E23", "S94", "A35", "T53", "R47", "P48", "L64", "K30", "H41", "C89", "L90", "M53", "U53", "Z51", "X65", "Y93", "S35", "N57", "P28", "S73", "H89", "T79", "T13", "D27", "R13", "P24", "Q26", "E38", "N91", "G84", "M78", "J46", "Y86", "N94", "J74", "J19", "H36", "F65", "X97", "L52", "C58", "Z40", "U35", "P41", "J13", "X17", "B21", "Y63", "R46", "S63", "E78", "L94", "D70", "R26", "N65", "H86", "S41", "F59", "R12", "A68", "U52", "H46", "V68", "F43", "M17", "B76", "P90", "Y12", "Y42", "P15", "R76", "S29", "R67", "L14", "D24", "Q15", "W19", "J92", "N96", "M24", "Z56", "H13", "B27", "C98", "Z74", "J34", "U12", "F58", "J72", "J69", "K62", "S31", "S24", "A34", "S25", "Z28", "R79", "Y87", "G87", "L62", "S39", "R65", "E52", "V65", "C65", "C96", "N67", "C34", "M30", "Z61", "H53", "C30", "M43", "V80", "Q79", "D38", "D42", "J89", "S83", "W32", "D89", "P57", "S45", "A12", "K25", "E98", "E93", "G27", "E79", "M89", "T94", "F78", "E21", "P31", "B87", "Z68", "K94", "D57", "R37", "Q56", "J79", "B20", "M94", "C80", "P80", "B70", "W58", "B80", "Z72", "K35", "T80", "Z38", "X49", "W40", "Y73", "A89"]}, {"image": "image_216.jpg", "codechart": "codecharts/code_chart_242.jpg", "codes": ["D94", "M12", "M23", "B95", "D39", "A16", "X56", "D51", "Z96", "J45", "M70", "S61", "V82", "S21", "H63", "Y79", "P70", "U80", "T41", "C87", "Q12", "U76", "B30", "A81", "C84", "E13", "M90", "T65", "P20", "V28", "X69", "X31", "U39", "A28", "G54", "C91", "W35", "U31", "K46", "D75", "Y36", "C31", "L72", "R34", "H52", "B89", "B32", "Y20", "F23", "U24", "Y10", "M39", "G89", "L31", "E64", "N64", "D93", "G63", "H80", "H16", "G18", "M64", "J10", "V74", "D20", "T67", "T75", "Z78", "L92", "Y32", "X57", "A41", "X82", "Q98", "Q30", "N93", "W87", "L75", "N86", "U65", "T25", "M29", "Y13", "G13", "K92", "W43", "S57", "Q81", "V59", "Y49", "M18", "H59", "A69", "K87", "P18", "A61", "A29", "R92", "Q58", "G93", "Z29", "H92", "U82", "Y46", "W93", "G76", "T36", "X89", "F45", "C76", "B59", "A96", "X27", "W27", "D19", "A95", "H10", "G83", "S13", "F64", "C59", "N37", "N62", "R17", "G80", "U72", "B71", "F26", "X87", "W96", "B54", "G98", "A57", "M95", "Z92", "E86", "C37", "X46", "X92", "C17", "Y48", "U68", "N50", "J91", "A79", "R50", "R43", "A86", "J85", "Q92", "H76", "G85", "T64", "Y71", "E35", "Y56", "F46", "T92", "K13", "R19", "U18", "K57", "D84", "D85", "E73", "D82", "Q31", "R61", "T42", "W73", "F17", "R24", "T85", "U10", "H40", "W13", "U20", "G65", "S78", "J75", "N80", "X74", "U75", "J95", "X35", "A24", "H82", "W41", "B13", "P35", "N74", "R48", "D72", "S23", "S38", "E92", "T28", "H81", "K17", "X61", "X16", "M56", "A75", "G62", "K50", "V69", "R90", "B94", "F28", "H20", "P74", "D86", "K97", "D96", "P84", "M46", "Z18", "G52", "N49", "Y70", "B35", "V47", "L15", "V16", "W14", "A21", "U43", "T16", "G60", "A82", "L49", "F73", "M20", "J14", "D47", "H12", "M84", "Y21", "H25", "F53", "U73", "K52", "D59", "C20", "W50", "S72", "S82", "J42", "D60", "U62", "S53", "S16", "T46", "F60", "F57", "E14", "N26", "L30", "E80", "A53", "F39", "M68", "E19", "N24", "W37", "H21", "J37", "A98", "H60", "Z12", "J49", "Y37", "Z30", "J52", "N81", "H72", "U46", "F52", "Y78", "G25", "M76", "H74", "K36", "D10", "K59", "Y25", "P75", "G17", "L87", "R45", "T53", "W31", "L90", "X41", "Y93", "U58", "C45", "A40", "K91", "K93", "Y60", "G78", "D92", "H62", "G68", "E34", "F36", "R63", "C49", "H36", "U27", "L52", "V37", "V86", "U29", "D34", "D67", "U35", "X17", "S56", "E25", "R78", "H96", "B73", "F59", "V68", "C27", "X90", "Z91", "U42", "C29", "V58", "E63", "E72", "R28", "M21", "N63", "Q15", "Z64", "P62", "X54", "Z56", "K10", "K12", "B83", "Q76", "J34", "F14", "R60", "F58", "E94", "F98", "B85", "A17", "H90", "S31", "E53", "K40", "M16", "M36", "B58", "D30", "R79", "J35", "Q73", "W97", "R23", "E37", "K86", "D64", "Z15", "R65", "V65", "P40", "F31", "L12", "C96", "R31", "L85", "E49", "B65", "D29", "G67", "X21", "M43", "W63", "N79", "S84", "N13", "U21", "Q48", "L43", "P57", "S45", "A12", "K25", "T26", "E98", "L19", "X15", "K26", "J86", "X50", "G27", "C71", "A72", "S62", "S14", "K41", "V43", "U91", "Q80", "E76", "H97", "F68", "M32", "K94", "R96", "R94", "K76", "F81", "V18", "R83", "B70", "R87", "F48", "T34", "A20", "D90", "M65", "B46", "J16"]}, {"image": "image_206.jpg", "codechart": "codecharts/code_chart_243.jpg", "codes": ["R85", "P76", "T37", "R38", "L60", "P16", "N41", "Q36", "M70", "U57", "S21", "C92", "N78", "G92", "U81", "B38", "Q52", "M19", "R86", "B30", "J39", "E13", "Z58", "Y84", "E57", "U39", "D71", "Y36", "R52", "K63", "Y59", "W82", "N48", "W45", "H52", "P46", "K14", "G89", "D12", "G63", "D93", "H16", "N95", "H78", "D32", "Y58", "A51", "A52", "H38", "X25", "P38", "V40", "X94", "X57", "P94", "Q98", "W24", "N46", "R98", "U65", "D83", "R82", "J32", "C25", "G13", "W43", "R93", "J67", "V83", "T60", "P52", "V59", "Z62", "E39", "K39", "B81", "M18", "P95", "U26", "K20", "T61", "T18", "D26", "W75", "G57", "Q58", "N36", "T89", "H92", "Y46", "E28", "T43", "G76", "T36", "Z13", "H57", "X89", "L54", "G82", "X27", "H10", "H93", "G83", "N14", "T95", "S13", "R27", "M75", "S68", "V76", "N87", "A47", "H58", "Q10", "A57", "Z63", "E86", "S52", "Z45", "Y94", "K73", "Y14", "L89", "R50", "R43", "Q16", "H61", "P69", "N71", "Q92", "N97", "T64", "X14", "Z16", "U18", "A83", "W54", "H85", "R54", "F49", "X12", "U89", "W69", "F95", "F17", "D37", "U20", "X48", "Q23", "Y19", "A45", "R69", "J43", "K89", "Y31", "U75", "W41", "J98", "H73", "X45", "N74", "K27", "N76", "X38", "T27", "R42", "F94", "B60", "D36", "X61", "X84", "H48", "K38", "V69", "R90", "A76", "C21", "F28", "C46", "N17", "F37", "J27", "W78", "H51", "D96", "B14", "Z18", "Z79", "C95", "B35", "S95", "G21", "V54", "S28", "G37", "F47", "L76", "D43", "R21", "T24", "T39", "L82", "S59", "H31", "C81", "W14", "Z27", "M52", "Z82", "Z69", "G42", "W84", "F90", "L49", "R58", "D23", "E42", "J14", "W61", "M84", "T71", "E36", "J31", "K52", "V48", "G20", "D60", "P89", "G26", "B50", "S64", "P26", "V49", "N53", "J40", "U19", "V92", "Q63", "F91", "Q45", "N26", "L29", "F39", "B41", "M68", "E19", "Q49", "G41", "M93", "B78", "B84", "A98", "J37", "Y27", "M98", "Z30", "J52", "Y97", "G47", "Q50", "G48", "M71", "W90", "G51", "K59", "V29", "L68", "E74", "C79", "Q13", "H65", "M54", "R71", "P58", "V93", "L17", "C39", "H54", "P42", "F54", "U58", "K84", "C63", "B53", "P39", "Z95", "S75", "R62", "R80", "T96", "N83", "U30", "B23", "P61", "G84", "C82", "M78", "G30", "H64", "N94", "Y86", "V96", "G38", "N89", "C49", "V37", "U29", "Z39", "U79", "U35", "W92", "A71", "J13", "M96", "E16", "T50", "S63", "R57", "K49", "W12", "R78", "P60", "J54", "Q28", "C93", "U52", "M57", "N35", "J64", "H56", "G53", "C29", "B12", "Y42", "R67", "K58", "G12", "F86", "P73", "U54", "C51", "Q15", "U34", "X54", "Z56", "B27", "Q65", "Z65", "Y76", "Q18", "Z74", "Q94", "F98", "Z43", "H90", "G50", "K62", "U36", "Q95", "A27", "Y83", "Z46", "R51", "F84", "U56", "M35", "T15", "D64", "V67", "S39", "F15", "E52", "R89", "V65", "V61", "D68", "H53", "Z61", "F63", "G67", "M43", "Q91", "A38", "F35", "S20", "W32", "M86", "H30", "S45", "F79", "R30", "W56", "L19", "X15", "U23", "X50", "G27", "R81", "C71", "A72", "U63", "T94", "V43", "Q80", "Z60", "H97", "J68", "V84", "M85", "J17", "Z68", "K76", "D57", "J83", "Q56", "G59", "M94", "P97", "B31", "C80", "R83", "J50", "W74", "P50", "P71", "Z73", "T80", "N84", "G28", "M65", "V94", "J28"]}, {"image": "image_281.jpg", "codechart": "codecharts/code_chart_244.jpg", "codes": ["P76", "S15", "B95", "A16", "A54", "W76", "M70", "S21", "U81", "Y79", "A87", "U80", "D87", "M19", "L39", "C87", "Q12", "G56", "A81", "M82", "H24", "M72", "K15", "T65", "X78", "Z70", "P37", "D71", "Y36", "K63", "V10", "P65", "M87", "U69", "F69", "R34", "H52", "A43", "N68", "X93", "M62", "G63", "S19", "B72", "P54", "G18", "M64", "L36", "K67", "V45", "U83", "R25", "H38", "T75", "Z78", "R32", "L92", "C56", "X82", "S58", "Q98", "B17", "L74", "T72", "J18", "L45", "E27", "R98", "N86", "Y95", "C47", "K23", "J76", "E48", "C25", "J67", "Y17", "T56", "K75", "W42", "H35", "D50", "H14", "E39", "T91", "A69", "K87", "P18", "R92", "Q85", "W75", "W70", "G93", "X43", "F19", "L10", "Z53", "X10", "T36", "H83", "F45", "Q41", "A95", "D19", "E32", "Z89", "H93", "E60", "N14", "X53", "X76", "R27", "S37", "N62", "X62", "E47", "X87", "S12", "A31", "Z23", "C72", "F42", "C37", "B90", "Y14", "N50", "A10", "R50", "K48", "Q16", "H61", "J85", "K19", "U49", "H75", "R53", "X14", "T10", "W81", "S47", "C75", "J25", "M69", "K13", "R19", "U71", "W54", "T51", "D84", "E73", "D82", "E50", "N34", "X48", "Q23", "N80", "R69", "V63", "T68", "Y31", "X35", "W41", "V32", "W79", "Y81", "V52", "H27", "P17", "N54", "F40", "H81", "V73", "X61", "P47", "A62", "C23", "X16", "D79", "X80", "D65", "W67", "H48", "E56", "C21", "F28", "E83", "F27", "C97", "Y51", "Y16", "C13", "G39", "D96", "M79", "Z79", "C95", "C61", "H94", "P10", "E67", "X34", "S95", "A94", "J61", "E24", "F47", "B98", "D43", "E40", "T39", "C81", "Y43", "M15", "Z47", "T16", "X37", "Z27", "A82", "L49", "M20", "E95", "W59", "N82", "T71", "D52", "H67", "V48", "C20", "L26", "W89", "S72", "S82", "U16", "Z25", "C60", "E46", "B50", "L35", "Y26", "V49", "S16", "B39", "P27", "H69", "C73", "B37", "F60", "U19", "U95", "J73", "E80", "L29", "A53", "B41", "F38", "K21", "B84", "K54", "D78", "V81", "G61", "B82", "Z12", "E75", "K71", "Z30", "E96", "Y97", "M76", "R73", "X40", "K59", "Y15", "Y25", "V13", "J41", "P45", "Q13", "Q96", "L24", "Q35", "G17", "S71", "C54", "S94", "Z87", "C39", "L90", "V70", "U53", "U13", "Y93", "N25", "S35", "G73", "V38", "P91", "X29", "K93", "X24", "V91", "G78", "P24", "C64", "G24", "N51", "N91", "P12", "C82", "L59", "J46", "F36", "J74", "M63", "B19", "U29", "C58", "P41", "B21", "Y63", "M96", "C68", "M13", "P32", "N65", "B62", "X98", "A68", "E59", "U52", "V60", "V42", "B51", "Y42", "R67", "K58", "C51", "P73", "F86", "U54", "K56", "C42", "E10", "J92", "U34", "Z56", "C48", "K10", "Z97", "K79", "B83", "G81", "U70", "J34", "E68", "F14", "F58", "F98", "V97", "B85", "H18", "B26", "Q75", "K40", "U36", "V78", "S92", "W80", "W21", "D30", "Z46", "K51", "A65", "J82", "J56", "D64", "L62", "F70", "E52", "R89", "F31", "N67", "L85", "S67", "U64", "C52", "A50", "X21", "M43", "G79", "W63", "S83", "S84", "Q34", "T38", "A12", "V25", "L19", "T84", "G46", "R81", "E79", "K41", "F18", "Q80", "F78", "H97", "J17", "Q24", "R94", "J79", "Q56", "B91", "B31", "Y23", "L28", "T63", "F50", "P80", "F32", "L84", "P71", "S27", "F67", "N84", "X49", "Y73", "P23", "A89", "B34", "P85", "S96"]}, {"image": "image_69.jpg", "codechart": "codecharts/code_chart_245.jpg", "codes": ["B86", "U51", "D95", "B67", "R38", "V57", "L60", "X32", "R68", "C85", "Y85", "K65", "J45", "U57", "Q39", "B38", "V46", "Q52", "Y72", "Z14", "W53", "U80", "C87", "R86", "B93", "W85", "T93", "M72", "L47", "F97", "P20", "X69", "X91", "Y41", "C91", "W71", "E70", "U59", "U15", "R52", "K63", "D31", "P65", "W82", "U17", "X79", "W45", "H52", "J90", "Y20", "X93", "V95", "K14", "L95", "D12", "L73", "B72", "Y74", "A56", "G18", "H78", "K67", "Y35", "T67", "X25", "P38", "Z78", "J53", "C90", "X94", "X57", "Y32", "D18", "B17", "A37", "U67", "N93", "S93", "H15", "R15", "K23", "D83", "Y13", "J32", "J67", "P56", "Y17", "N23", "W42", "A25", "V59", "E39", "T69", "A69", "A29", "N32", "Q84", "W75", "G57", "E29", "B48", "G14", "Z13", "X89", "B59", "F62", "X27", "D19", "A95", "Z42", "X18", "X53", "X76", "M75", "D54", "N10", "V72", "G80", "V76", "U47", "B71", "E47", "Z86", "S12", "H58", "L65", "C72", "Z63", "S52", "X46", "C12", "X81", "Y48", "W98", "G10", "J58", "R50", "A86", "S97", "H75", "Q38", "E87", "X14", "M69", "E15", "P92", "G29", "T92", "K13", "H87", "U32", "F49", "X12", "E73", "R61", "E50", "P63", "U10", "B15", "G65", "W36", "A45", "N80", "X58", "K61", "V17", "B10", "H34", "W79", "Y52", "V52", "H27", "S38", "H81", "B60", "H43", "Z80", "C23", "T97", "X84", "A75", "K64", "K38", "E26", "K50", "V69", "Y64", "E58", "H51", "D86", "U48", "P67", "K97", "G39", "W26", "Q25", "M92", "Q51", "H70", "D73", "P10", "T70", "Y70", "F41", "B92", "J61", "G37", "J30", "B98", "A30", "D43", "V47", "L15", "Q60", "V16", "C81", "P96", "T45", "X37", "Q59", "G60", "M97", "H50", "K32", "Z69", "R58", "W59", "M58", "J14", "E42", "Y21", "A97", "D52", "E36", "C83", "D59", "W39", "G20", "Z49", "U16", "S82", "R40", "S53", "G26", "P26", "Q61", "N61", "Y80", "B36", "F57", "V92", "D81", "F91", "Q63", "P53", "A36", "H91", "U95", "Q17", "B41", "H21", "H60", "V81", "W68", "J51", "Y27", "T32", "M60", "F52", "Y78", "H74", "S48", "S46", "Y38", "V29", "P75", "C79", "Q13", "M54", "J48", "C54", "D97", "T53", "Y53", "F24", "B75", "N25", "G74", "S35", "V38", "P14", "F54", "P28", "K91", "P39", "Z95", "X24", "S75", "Q64", "U30", "B23", "N51", "N91", "L93", "T52", "M81", "F61", "J74", "P87", "G38", "M63", "V24", "F65", "W52", "W57", "N70", "K16", "A71", "B40", "E16", "C68", "F56", "M13", "N47", "X30", "H96", "N65", "J54", "F87", "B73", "S85", "X98", "V60", "H46", "T76", "C27", "M17", "G53", "E65", "C29", "E61", "G72", "R28", "E63", "S29", "S50", "N63", "G12", "P29", "C51", "W19", "P62", "C48", "Y91", "S87", "B83", "F14", "J72", "Q74", "V97", "M47", "C32", "D61", "X85", "J69", "S31", "H79", "C40", "L38", "A34", "M26", "B69", "V39", "R79", "Q73", "F84", "X51", "Y24", "M35", "J56", "G87", "M31", "R65", "D46", "C65", "Y54", "D68", "A46", "S67", "B65", "Z61", "C52", "F63", "X21", "S20", "W62", "Q79", "D42", "M67", "U21", "T21", "S45", "A12", "T73", "J70", "N27", "S81", "S14", "M89", "F18", "E76", "P31", "R94", "K76", "R37", "F81", "L13", "Y23", "L28", "B63", "P80", "R87", "B80", "P71", "T34", "K35", "N84", "X49", "M65", "L40", "U74", "J16"]}, {"image": "image_58.jpg", "codechart": "codecharts/code_chart_246.jpg", "codes": ["X47", "P76", "S15", "R38", "X32", "Y85", "Z96", "A54", "M70", "Q93", "S21", "N78", "C92", "H63", "V46", "V75", "K18", "Z10", "W25", "C87", "U76", "A70", "A81", "E13", "Z58", "E82", "X39", "U31", "R52", "W82", "F21", "C31", "U17", "R18", "V34", "L72", "A43", "N68", "B32", "A49", "F23", "G94", "K72", "A78", "M39", "L31", "E64", "N64", "V26", "J71", "L95", "H16", "B72", "G23", "V45", "Y35", "Y58", "A51", "X59", "D20", "P38", "R32", "C90", "Y32", "U45", "N46", "L78", "G49", "K23", "J32", "H47", "F12", "S57", "V83", "Q81", "K75", "R59", "G95", "T91", "A69", "E20", "K20", "T61", "P18", "P82", "Q84", "N32", "G57", "G93", "A26", "G14", "L97", "F72", "Y89", "L10", "G76", "X20", "H57", "A19", "S79", "X89", "Q54", "X52", "B59", "F62", "E51", "T57", "W47", "Z89", "X53", "A48", "A85", "Z23", "C38", "L65", "W64", "C72", "M95", "X46", "X92", "Y48", "L89", "W98", "M10", "V19", "L32", "A79", "K24", "N97", "U49", "Q38", "Q57", "Y71", "T10", "Y56", "M69", "C75", "F46", "Q21", "X26", "H85", "Z21", "D98", "X12", "E73", "D82", "S96", "W69", "E50", "T42", "T85", "Q23", "N69", "G36", "U75", "A24", "W41", "J98", "K74", "F20", "Q62", "U60", "S23", "K27", "N76", "M25", "R42", "T23", "F94", "D91", "K17", "D45", "U28", "S60", "Z80", "C23", "T97", "D65", "K64", "A76", "F28", "N17", "F37", "P74", "L53", "Y16", "H51", "N20", "P67", "K97", "C15", "T48", "W26", "Q25", "B14", "E12", "C95", "C61", "D73", "U38", "H39", "N49", "A94", "S28", "J30", "X64", "C81", "W10", "Y43", "M15", "Z47", "Q59", "M97", "A82", "K32", "L49", "W59", "M84", "N82", "A97", "D52", "H25", "F53", "D59", "W39", "G20", "L26", "Z49", "S72", "S82", "X95", "D17", "N39", "U62", "E46", "G26", "P89", "Q61", "K37", "J40", "N61", "M42", "V92", "Q29", "R29", "F91", "U94", "P53", "E80", "M68", "Z24", "M93", "V81", "G61", "Y27", "E75", "M98", "N81", "E96", "Q50", "M60", "J62", "M71", "D10", "T49", "G51", "M14", "P75", "L24", "G17", "R71", "G43", "E23", "R45", "A35", "T53", "P21", "E54", "C89", "L90", "Y53", "X65", "Y93", "P91", "V98", "F54", "P28", "K84", "K91", "Z95", "X24", "T96", "D27", "R13", "P24", "Q64", "B23", "E38", "W16", "N51", "V27", "P61", "C82", "L59", "F61", "G30", "H64", "E34", "V35", "M63", "Q40", "B19", "C16", "W57", "Y75", "C58", "Z40", "F16", "D67", "Z39", "A71", "J13", "X17", "Y63", "E16", "C68", "E25", "F56", "A73", "L94", "D70", "S43", "N65", "F87", "P68", "S41", "F59", "Z36", "U52", "D62", "V68", "P59", "W86", "M17", "B76", "A32", "E72", "R76", "R67", "F86", "P73", "K70", "K56", "J92", "N96", "M24", "A64", "Q71", "R74", "Z97", "S70", "B83", "F30", "H49", "E68", "J72", "J60", "D61", "H90", "Q86", "K62", "E53", "H79", "V78", "M26", "S92", "S25", "B24", "R64", "J82", "X51", "D21", "J56", "A67", "F70", "B97", "E52", "C65", "F83", "R31", "E49", "D16", "S67", "M30", "F63", "F35", "K82", "Q79", "W60", "S84", "M86", "M74", "T30", "D89", "Q46", "T38", "S45", "T26", "W56", "G40", "T84", "R81", "F18", "M50", "H97", "C50", "J17", "R94", "D57", "C26", "G59", "M94", "P97", "C80", "T63", "P80", "L84", "J78", "Z38", "S27", "D90", "J26"]}, {"image": "image_335.jpg", "codechart": "codecharts/code_chart_247.jpg", "codes": ["R85", "X47", "B67", "D94", "B28", "D39", "X32", "A16", "R68", "D51", "S21", "N78", "G92", "K83", "M37", "V75", "K18", "Q12", "U76", "A70", "J39", "E13", "M72", "L47", "P20", "F97", "Z70", "E82", "G54", "U15", "Y36", "R52", "K63", "U90", "M38", "L72", "N30", "L80", "F69", "A90", "A49", "V95", "A78", "E45", "N64", "J71", "D12", "H78", "R75", "J47", "Q97", "U83", "T67", "H38", "J53", "R32", "V40", "B17", "U67", "L50", "W87", "Y92", "L75", "L45", "H15", "K23", "Y13", "W43", "W49", "V59", "M18", "T91", "H59", "A69", "T61", "B47", "A29", "W75", "G93", "D14", "W65", "W93", "L79", "Z53", "Z13", "H57", "X52", "S32", "F45", "P30", "B59", "W47", "H10", "H93", "G83", "Q69", "X53", "S80", "M75", "S68", "A85", "T82", "X62", "F26", "Z86", "Z23", "K28", "Z63", "F25", "S52", "S54", "X28", "X46", "X92", "X81", "K42", "Z45", "A10", "F82", "W51", "J58", "R43", "J93", "K24", "S98", "A86", "T64", "R53", "G32", "N38", "Y69", "L41", "J25", "M69", "Z98", "H23", "D84", "E73", "T42", "W73", "Q32", "C41", "D37", "X48", "G65", "Q23", "Y19", "X58", "N80", "E97", "Z93", "B10", "L18", "U75", "Y52", "X45", "B49", "Q62", "Y81", "S23", "N76", "M25", "P17", "E92", "T27", "K78", "T23", "F94", "H81", "D36", "S65", "X61", "D45", "Z80", "A42", "R39", "L21", "C21", "P13", "F28", "F37", "C97", "B64", "J27", "L96", "U86", "G39", "T48", "P10", "T70", "S86", "G21", "N15", "C78", "E24", "U25", "J30", "A30", "T78", "C62", "S59", "D74", "H31", "Q60", "V16", "A21", "T45", "T16", "D35", "N58", "Z27", "D56", "H50", "X13", "G42", "M20", "Y98", "C94", "B45", "N82", "Y40", "L61", "J31", "C83", "U73", "D59", "C20", "W89", "X95", "C60", "E46", "S53", "L35", "Q42", "S16", "L46", "C43", "V92", "E84", "R29", "Q29", "U94", "H91", "P53", "Z59", "M68", "E19", "Z24", "W37", "M93", "H21", "K54", "H60", "T35", "D49", "T32", "N81", "M60", "F52", "A59", "W46", "D10", "X40", "M14", "Y25", "V13", "E74", "P45", "L24", "M54", "Q96", "R71", "D97", "W38", "P21", "R36", "P48", "Y53", "Z51", "X41", "X65", "G74", "N19", "F71", "G73", "V38", "P28", "A40", "C63", "P39", "Y57", "Z95", "C14", "R62", "G78", "H62", "B23", "W16", "N45", "P61", "F36", "P87", "V96", "Z34", "G38", "U96", "U27", "C16", "U29", "Y75", "Z26", "M80", "S56", "W95", "C68", "T50", "Y96", "M13", "A73", "X42", "R26", "S43", "X71", "Z90", "C93", "F59", "U52", "T20", "E69", "N35", "P81", "J64", "F43", "H56", "B76", "R70", "V58", "Q78", "S50", "M21", "C57", "P29", "C51", "D24", "Q15", "C42", "J92", "Z64", "C48", "B27", "T47", "K10", "Z97", "S70", "F10", "K69", "F98", "D61", "X85", "G34", "Q86", "H18", "K40", "Q95", "W80", "Y83", "J96", "R79", "Q73", "M35", "A67", "D64", "L62", "S42", "V65", "V64", "S91", "F83", "S36", "P25", "T17", "M30", "B65", "Z61", "A50", "C30", "F35", "S20", "W63", "Q34", "D89", "D76", "K43", "T38", "C24", "L19", "J86", "T84", "N27", "E93", "X50", "S62", "E79", "M50", "S69", "F68", "J23", "D25", "G97", "R96", "K76", "C26", "C86", "J83", "Q56", "B20", "B91", "L13", "H17", "W74", "B63", "N42", "R87", "B80", "P50", "K35", "S27", "F67", "D41", "N84", "U74", "J26"]}, {"image": "image_346.jpg", "codechart": "codecharts/code_chart_248.jpg", "codes": ["B86", "P76", "D94", "U40", "D39", "N41", "Z96", "K65", "M70", "U57", "Q93", "Q39", "H63", "Y79", "V46", "Q52", "V75", "M37", "J94", "P70", "T41", "B96", "Z57", "P64", "G56", "A70", "H24", "J39", "L47", "K15", "T65", "X69", "Y84", "Y41", "G54", "D58", "G69", "U90", "F21", "Z81", "M38", "U69", "F69", "H52", "R41", "Y20", "X93", "K53", "E45", "Z94", "M62", "R75", "B79", "X59", "A51", "D20", "V40", "X94", "X57", "B17", "U67", "L50", "D69", "D53", "N93", "G49", "U65", "D83", "A23", "S57", "T60", "T56", "P52", "W49", "V59", "R59", "K39", "B81", "N32", "W75", "T87", "Q58", "G93", "E29", "K34", "G14", "L97", "J87", "A14", "P78", "Z13", "P30", "G82", "Y68", "X27", "W27", "E51", "W47", "Z89", "X18", "R27", "N62", "A47", "U72", "Z86", "H58", "Z23", "N21", "Z92", "Z63", "R97", "X28", "G71", "Y14", "L89", "F82", "W51", "G10", "K48", "R43", "H95", "Q16", "Z17", "Q92", "X36", "E87", "X14", "T10", "C75", "Z16", "X75", "W54", "Z98", "F49", "H23", "R24", "C41", "D37", "W13", "U20", "G65", "Q23", "W94", "Y19", "G36", "S74", "L18", "X35", "K74", "B13", "P35", "S89", "B49", "Q62", "F20", "D72", "K27", "V52", "T29", "M25", "V73", "T40", "A62", "X16", "T97", "X84", "M56", "W67", "E56", "G62", "L21", "Y64", "E58", "E83", "N17", "F37", "P74", "C97", "C13", "C15", "V90", "M46", "M92", "H70", "E12", "H29", "S86", "B92", "S95", "G21", "G35", "L76", "E40", "R21", "S59", "C81", "T45", "Q59", "D56", "H50", "T14", "Z69", "R58", "M20", "C94", "D47", "B45", "N29", "Y40", "L61", "H67", "P98", "D59", "Z49", "Z25", "Y26", "N53", "J40", "C73", "C74", "B37", "M42", "P43", "P19", "F91", "A36", "N52", "L30", "Q17", "B41", "M68", "H21", "G61", "Z12", "N81", "H72", "U46", "Q50", "G48", "V12", "M76", "W46", "K36", "S48", "T49", "K59", "N12", "H65", "M54", "D97", "J48", "E23", "G70", "S94", "R45", "T53", "Q70", "Z87", "Y28", "Z19", "Z51", "N25", "N19", "S35", "N57", "C36", "F54", "P28", "A40", "R16", "B53", "Y57", "C14", "H89", "U98", "K93", "R80", "T96", "N83", "D27", "G78", "W18", "N51", "G24", "T52", "L70", "Q90", "F61", "E34", "V35", "N94", "V53", "J74", "P87", "N56", "J19", "Q40", "X97", "F96", "X23", "W57", "N70", "D67", "L63", "J59", "T86", "V41", "E25", "R46", "Y96", "A73", "L98", "L94", "Z32", "N47", "P32", "R26", "S43", "W12", "H96", "F87", "J54", "Q28", "B62", "V36", "Z36", "V60", "T20", "D62", "V42", "N35", "J64", "V51", "U42", "Z52", "P90", "B12", "R70", "Q78", "G72", "A32", "E72", "B42", "R76", "N31", "G12", "U54", "C51", "E10", "P62", "X54", "Z56", "Z97", "K12", "Q65", "Y76", "G81", "C98", "F10", "F58", "Z31", "J72", "J60", "E94", "S31", "A34", "S25", "V15", "K51", "V39", "A65", "J82", "X51", "W72", "R65", "D28", "F31", "Y54", "M30", "A50", "C30", "C52", "X21", "V80", "S20", "Q79", "N79", "D38", "S83", "E17", "W60", "Q19", "U21", "D76", "K43", "Q46", "N73", "T38", "K25", "C24", "T26", "L19", "Z35", "G40", "E93", "N27", "G27", "S81", "R81", "U63", "F78", "H97", "K81", "J23", "M85", "R37", "G59", "B91", "M94", "B31", "P97", "Y23", "D48", "F50", "N72", "F48", "L84", "J78", "P71", "M34", "L40", "J16"]}, {"image": "image_316.jpg", "codechart": "codecharts/code_chart_249.jpg", "codes": ["D95", "X47", "P76", "M12", "E43", "L60", "A16", "Y85", "X56", "D51", "Q36", "W76", "V82", "N78", "C92", "U81", "V46", "K83", "Y72", "V75", "P70", "W25", "J94", "T41", "R86", "B93", "A15", "P64", "G56", "C84", "L47", "R95", "Y84", "E57", "W35", "K29", "G69", "Y36", "X67", "V34", "N68", "F23", "X93", "X70", "G89", "L95", "M62", "H80", "B72", "G23", "A56", "P54", "B79", "U83", "X59", "V31", "U37", "X25", "R32", "L92", "Y32", "C56", "Q47", "Q98", "U67", "L75", "J76", "E48", "Y13", "A23", "P56", "F12", "Y17", "T60", "W49", "V59", "H35", "Z62", "H59", "P95", "N32", "E31", "C67", "E29", "K34", "L97", "T43", "J87", "P78", "Q54", "A19", "S79", "X52", "S32", "A96", "U93", "C28", "E32", "Z42", "E60", "G83", "F64", "N87", "T82", "Y61", "Z86", "L65", "A57", "W64", "K28", "Z92", "F89", "X28", "C17", "X81", "Z45", "Y48", "W98", "L32", "W51", "P36", "R50", "F34", "K47", "Z17", "A86", "S97", "T64", "H75", "E87", "G32", "Z84", "X14", "N38", "S47", "M69", "A83", "Z41", "U32", "D98", "X12", "F49", "D84", "R61", "C41", "H40", "W13", "U20", "D63", "A45", "R84", "E97", "S74", "T68", "W41", "H34", "B13", "P35", "X45", "A91", "W79", "S89", "R48", "U60", "Y81", "M25", "X38", "K78", "R42", "F94", "D80", "V73", "K17", "P47", "W67", "H48", "V69", "R90", "Y64", "F28", "F85", "F27", "N17", "B64", "L53", "C13", "R56", "V90", "G15", "E12", "C95", "C61", "H29", "Y70", "B92", "L91", "A94", "G35", "A39", "A30", "L76", "C62", "Z71", "S59", "D74", "H31", "Y30", "U43", "P96", "Q59", "Z27", "M52", "G42", "Y98", "E95", "H12", "Y40", "C83", "H25", "W39", "G20", "L26", "Z49", "L67", "C60", "R40", "S53", "G26", "P26", "L58", "Q42", "N53", "N61", "B39", "C73", "P27", "F60", "P43", "E84", "Q63", "P53", "N52", "Q45", "J73", "Q17", "E80", "C18", "F39", "L29", "B41", "M68", "F38", "K21", "J37", "H60", "D78", "M45", "G61", "J49", "G16", "K71", "Z30", "B61", "Y97", "U46", "M60", "V12", "T59", "T19", "T49", "L81", "P58", "R72", "S71", "S30", "H41", "B68", "V70", "F24", "F71", "S35", "P91", "A93", "U58", "V71", "R80", "J15", "L93", "T52", "M78", "J46", "V85", "H64", "E34", "V35", "J19", "Q40", "X97", "F96", "D34", "U79", "Z39", "B40", "M80", "T86", "Z83", "E16", "R46", "E78", "F56", "L98", "X72", "E71", "K49", "J54", "V36", "S85", "V60", "U52", "D62", "E69", "M57", "N35", "U92", "W86", "B76", "Y42", "Q78", "R28", "R76", "R67", "B42", "N63", "G12", "L14", "U54", "P73", "C51", "N96", "X54", "C48", "H13", "R74", "S87", "K79", "Q76", "Q65", "J81", "Z65", "Z74", "J34", "E68", "J60", "F98", "L20", "M47", "A17", "J69", "Q86", "K62", "S31", "Q95", "C40", "M26", "Z28", "K31", "U56", "K60", "Y24", "D21", "M35", "T15", "Q14", "L62", "W72", "F70", "R65", "R89", "S91", "C96", "R31", "L85", "P25", "D16", "S67", "M30", "Z61", "D29", "U64", "A50", "H53", "S20", "W62", "N16", "J89", "Q34", "M86", "Q48", "T30", "Q46", "K43", "N73", "S45", "A12", "K25", "R30", "G40", "U23", "K26", "U91", "F18", "F68", "M85", "C50", "M32", "K94", "J83", "J79", "F81", "P97", "J50", "Y23", "N72", "B70", "N42", "W58", "P71", "P86", "D90", "B34", "B46", "V94"]}, {"image": "image_234.jpg", "codechart": "codecharts/code_chart_250.jpg", "codes": ["B67", "D95", "D94", "V57", "E30", "N41", "D51", "Z96", "K65", "S61", "N78", "G92", "V46", "P70", "A87", "T41", "Z57", "L39", "B96", "W85", "A15", "P64", "B30", "J39", "Z70", "E18", "X91", "E82", "Y41", "U59", "D71", "G69", "U15", "P65", "M87", "N48", "L72", "F69", "A43", "B32", "F23", "K53", "M83", "X70", "L31", "E64", "G63", "L73", "S19", "H78", "R75", "K67", "Y58", "R25", "U37", "T75", "P38", "R32", "C90", "U14", "R98", "K45", "J76", "K23", "P56", "Q81", "K75", "V59", "R91", "H35", "R59", "D50", "K39", "M18", "K20", "T18", "P82", "A29", "W75", "Q58", "K34", "E28", "J38", "F72", "X20", "P30", "T57", "C19", "E32", "X76", "S13", "R27", "D54", "U47", "R17", "V76", "Y61", "B71", "Z86", "B74", "F76", "C38", "L65", "K28", "E86", "F89", "S52", "C17", "K42", "Y94", "U41", "Y48", "G71", "K73", "N50", "M91", "W51", "J91", "R50", "F34", "J24", "S98", "X36", "U49", "T64", "Q38", "E87", "Y69", "Y56", "L41", "M69", "F46", "Z16", "T92", "U18", "H87", "Z98", "U32", "Z21", "H37", "R54", "D84", "W69", "E50", "F17", "C41", "U10", "T85", "W13", "W36", "W94", "E97", "B56", "J43", "L18", "X74", "X35", "A24", "H34", "H73", "B13", "P35", "S89", "A91", "S40", "Q62", "V52", "M25", "N54", "F40", "R42", "T40", "C23", "M56", "X80", "H48", "K64", "G62", "V69", "R39", "X83", "N17", "Y51", "W78", "U86", "P67", "C15", "T48", "M92", "S18", "P10", "H29", "T70", "Y70", "F41", "B35", "S95", "N15", "G35", "F47", "J30", "B98", "R21", "Z71", "S59", "Y30", "U43", "M15", "T45", "T16", "N58", "Z82", "F73", "C94", "W23", "T71", "U73", "D59", "V48", "W50", "G20", "X95", "D60", "L35", "Q42", "Y26", "V49", "N53", "S16", "Q61", "C73", "H69", "C74", "L46", "Y80", "M42", "E84", "R29", "E81", "E80", "F39", "Z24", "N24", "G41", "B82", "J51", "T32", "G47", "T59", "H74", "H28", "K36", "W90", "V62", "G51", "F29", "K59", "W83", "R71", "C54", "E23", "Q70", "P48", "E54", "L64", "H68", "Y28", "V23", "Y53", "Z19", "H54", "P42", "N19", "V98", "F54", "C45", "K91", "X29", "B53", "P39", "X24", "U98", "R62", "R13", "P24", "Q26", "H62", "L69", "G24", "L93", "C82", "F61", "G30", "P87", "Z34", "N56", "V24", "C49", "H36", "Q40", "G64", "U27", "U29", "D34", "J20", "Z26", "T31", "M80", "B21", "Y63", "V41", "V21", "R46", "S63", "L98", "D70", "W12", "F87", "Q28", "T62", "B62", "L27", "S85", "Z36", "G91", "U92", "C27", "W86", "G53", "U42", "A74", "E63", "R67", "M21", "G12", "P93", "P29", "D24", "C51", "N90", "K56", "J92", "A64", "Q71", "R74", "B27", "K10", "K12", "Z65", "J80", "Q18", "F14", "R60", "J72", "L20", "Y50", "Z43", "M47", "C32", "H90", "V89", "H18", "B26", "Q75", "F13", "H79", "C40", "A27", "B69", "W80", "B58", "D30", "C35", "J35", "K60", "E37", "M35", "T15", "Y87", "V67", "Q14", "S42", "D28", "F31", "C96", "N67", "S91", "F83", "R31", "D68", "F75", "C52", "C30", "A38", "K82", "N79", "D42", "J89", "S83", "E17", "U21", "M74", "T30", "D76", "Q46", "T38", "V25", "B29", "H84", "X15", "G40", "N27", "E79", "F18", "M50", "K81", "G58", "J23", "D57", "C86", "J83", "B91", "M94", "W28", "F81", "R87", "P71", "Z38", "L23", "F67", "S27", "M65"]}, {"image": "image_295.jpg", "codechart": "codecharts/code_chart_251.jpg", "codes": ["B86", "U51", "B67", "P76", "D94", "M23", "B95", "V57", "P16", "D51", "B38", "Y79", "K18", "U80", "B96", "D87", "Q12", "W85", "A15", "U76", "P64", "J39", "C84", "L47", "P20", "C91", "U31", "E41", "U59", "Y65", "D71", "G69", "D31", "N48", "C31", "F21", "W45", "L80", "R34", "B89", "R41", "J90", "F23", "Y10", "V95", "X70", "G63", "P54", "N95", "L36", "V45", "U83", "V74", "T67", "X25", "J53", "X94", "U14", "L92", "P94", "X82", "S58", "Q98", "L78", "G49", "E27", "Y95", "L37", "K23", "D83", "M29", "C25", "W43", "P56", "Y17", "K75", "P52", "V59", "H35", "U87", "P95", "B47", "P18", "A61", "A29", "Q84", "K34", "G14", "L97", "X10", "P78", "H83", "X20", "H57", "A19", "K68", "X89", "Q54", "J84", "C76", "E51", "F80", "M40", "X53", "X68", "S13", "C59", "N37", "N10", "N62", "A47", "X87", "B71", "Z86", "F26", "A31", "B54", "Q10", "Z63", "C37", "F89", "B90", "U68", "A10", "V19", "W51", "J93", "Q16", "Z17", "A86", "N97", "K96", "Q38", "W81", "N38", "E35", "L41", "Z16", "R19", "A83", "H87", "X12", "D85", "W69", "T42", "R49", "T85", "C41", "Q23", "B56", "J43", "K61", "V63", "V79", "S74", "B16", "B10", "L18", "W41", "J98", "P35", "A91", "S40", "S23", "V52", "N54", "K78", "T23", "T28", "V73", "D36", "P47", "U28", "D45", "A62", "Z80", "X84", "D65", "E56", "K38", "K50", "R90", "R39", "A76", "F28", "E83", "F85", "P74", "C97", "Y16", "D86", "R56", "E12", "U38", "T70", "E90", "E67", "B92", "S86", "G21", "A94", "C78", "S28", "U25", "D43", "L15", "T24", "D74", "Y30", "W10", "Y43", "W84", "F90", "Q67", "M58", "D47", "M84", "N82", "T71", "Y40", "E36", "J31", "M48", "H25", "P98", "F53", "V48", "H42", "S82", "X95", "Z25", "R40", "B50", "P26", "L35", "L58", "V49", "K37", "T46", "B36", "E84", "Q29", "F91", "N43", "Q45", "G86", "E19", "Q49", "T35", "B82", "Z12", "D49", "Y27", "K71", "J52", "Y97", "G48", "J62", "G25", "W46", "T19", "S48", "T49", "F29", "L81", "C79", "G17", "P58", "S71", "S94", "A35", "R47", "P21", "V87", "L64", "L25", "L71", "Z19", "X41", "N19", "C36", "A40", "P39", "V71", "H89", "U98", "T96", "T13", "R13", "H62", "W18", "N91", "P61", "G84", "F61", "G30", "F36", "V53", "J74", "J19", "R63", "N89", "C49", "U96", "Q40", "B19", "G64", "F96", "X23", "U29", "D67", "J20", "W92", "L63", "T31", "S56", "E25", "R57", "N47", "X30", "H96", "J54", "Q28", "L27", "R12", "Y18", "A68", "U52", "G91", "E69", "W86", "M17", "H56", "V51", "Y12", "V14", "E61", "A74", "R67", "M21", "C42", "J92", "N96", "Z64", "P62", "X54", "Q71", "Z56", "B27", "J12", "Z97", "Y76", "Q65", "J80", "E68", "J72", "J60", "C32", "G50", "S31", "Q75", "E53", "C40", "B52", "S92", "J97", "V15", "D30", "R79", "J35", "F84", "Y24", "W30", "J56", "Q14", "S42", "F70", "V64", "L12", "C96", "S91", "Y54", "L85", "E49", "D16", "T17", "Z61", "U64", "C30", "A38", "W62", "W63", "S83", "J89", "Q48", "P57", "T21", "N73", "S45", "E98", "J70", "R30", "G40", "A72", "K41", "E76", "J23", "J17", "D25", "Q24", "D57", "K76", "C26", "D40", "Q56", "G59", "B20", "F81", "W28", "B31", "M94", "R83", "P97", "N42", "M34", "G75", "N84", "G28", "D90", "A89", "M65", "B34"]}, {"image": "image_393.jpg", "codechart": "codecharts/code_chart_252.jpg", "codes": ["B86", "B67", "T37", "S15", "W17", "C85", "Y85", "N41", "Z96", "K65", "V46", "Y72", "K18", "M19", "C87", "Q12", "Y47", "B30", "H24", "M90", "Q68", "V28", "Z70", "Y41", "G54", "Q87", "D71", "K63", "R52", "R18", "U69", "L80", "B89", "P46", "X70", "E45", "L31", "D12", "L73", "S19", "N95", "G18", "K67", "D32", "U83", "A52", "U37", "T75", "Z48", "Y45", "L92", "C56", "Q98", "U45", "T72", "L50", "D53", "L75", "Y92", "H15", "E27", "K45", "K23", "J57", "W43", "R91", "G95", "B81", "T91", "T74", "K87", "K20", "X96", "D26", "R92", "G57", "D14", "T89", "B48", "G14", "U82", "W65", "J38", "J87", "L10", "Z53", "T36", "P78", "S79", "S32", "F45", "C76", "Y67", "U93", "F62", "C28", "Q41", "C19", "H93", "X18", "N14", "M40", "S80", "T95", "X68", "A48", "U47", "V76", "T82", "S12", "B74", "A31", "Q10", "C72", "Z63", "X73", "S52", "C12", "M10", "W98", "R43", "F34", "J93", "Q92", "X36", "S97", "Q57", "X14", "N38", "W81", "E35", "X75", "P51", "K13", "U18", "T51", "U32", "D98", "D84", "E73", "R61", "N34", "R24", "H40", "B15", "X48", "W36", "A45", "X58", "V79", "Y31", "X74", "A24", "H34", "J98", "V32", "W41", "K80", "H73", "B13", "S89", "A91", "Q27", "T12", "T28", "N54", "T23", "F40", "D91", "D36", "U28", "T98", "X80", "A42", "H48", "K64", "E26", "A76", "L21", "C21", "P13", "F28", "C46", "H20", "F85", "N17", "F27", "P74", "H51", "U86", "R56", "P67", "V90", "M79", "M46", "M92", "H70", "E12", "H39", "E67", "L91", "B35", "C69", "N15", "E24", "V54", "A39", "U25", "A30", "R21", "L82", "H31", "V16", "C81", "U43", "G60", "Z27", "M52", "D56", "A82", "H50", "C94", "M58", "E42", "D47", "Y40", "L61", "M48", "H25", "D59", "V48", "H42", "U16", "J42", "N39", "U62", "S17", "Q42", "N53", "N61", "C73", "H69", "C74", "B36", "Y80", "P43", "V92", "U94", "F91", "L30", "N24", "D78", "S76", "J49", "H19", "Y97", "E96", "H72", "U46", "F52", "Y78", "W46", "P79", "V29", "Y25", "Y15", "P75", "P58", "D97", "J48", "R45", "V93", "L17", "P21", "Z87", "S30", "L90", "M27", "G74", "S35", "G73", "A93", "U58", "X29", "R16", "P39", "E62", "C14", "X24", "U98", "V91", "R80", "N83", "H62", "L69", "N51", "T52", "P12", "M78", "M81", "G30", "V85", "H64", "S26", "Y86", "S49", "J74", "N56", "M63", "G38", "V20", "H36", "G64", "F96", "V37", "V86", "C58", "U79", "J20", "U35", "P41", "U78", "S56", "T86", "V21", "S63", "L98", "W34", "E71", "N47", "X71", "S85", "H86", "V60", "H46", "E59", "V68", "V42", "N35", "P59", "U92", "W86", "Z91", "P15", "R76", "N31", "K90", "G12", "L14", "U54", "D24", "N18", "Q15", "K56", "E10", "N96", "M24", "C48", "B27", "J12", "Y91", "K12", "B83", "Q18", "U12", "Q74", "L20", "Y50", "Z43", "A17", "B26", "M36", "S92", "A34", "B69", "B58", "L42", "J96", "H32", "Y24", "W72", "D28", "R89", "V64", "G67", "C30", "X21", "V80", "Q91", "G79", "D38", "N16", "S83", "S84", "Q34", "Q48", "M74", "F51", "P57", "T21", "T38", "S45", "J70", "G40", "U23", "G46", "C71", "K41", "M89", "S69", "H97", "J23", "D25", "B87", "W20", "B20", "M94", "P97", "F81", "T63", "D48", "W74", "Y62", "F32", "B80", "Z72", "Z73", "Z38", "A20", "F67", "Y73", "D90"]}, {"image": "image_190.jpg", "codechart": "codecharts/code_chart_253.jpg", "codes": ["S15", "W15", "W17", "X32", "R68", "N41", "E30", "X56", "Z54", "Q39", "Y72", "K18", "P70", "Q12", "B30", "A70", "L34", "K15", "V28", "U39", "X91", "Y41", "U59", "K46", "G69", "R52", "V10", "D31", "K63", "N48", "L80", "X79", "R34", "B32", "A49", "Y10", "L86", "A78", "M39", "E45", "E64", "S19", "G18", "H78", "V45", "V74", "X59", "R25", "V31", "H38", "T75", "C10", "U61", "R32", "X82", "T72", "L74", "J18", "D53", "Y92", "H15", "L37", "U65", "Y13", "J57", "S57", "W49", "R91", "Y49", "E39", "T69", "B81", "M18", "T74", "K87", "E20", "P34", "M73", "P82", "C67", "Z29", "N85", "T43", "W93", "Y89", "J87", "X20", "S79", "X52", "P30", "S32", "C76", "A96", "E51", "Q41", "T57", "W47", "E32", "F80", "M40", "X53", "A48", "R27", "S68", "V72", "G80", "A85", "X62", "F26", "B71", "B74", "C38", "K28", "Z92", "Z63", "J21", "C37", "S54", "B90", "X92", "K42", "Y14", "W98", "R43", "H95", "J93", "N60", "Q92", "R20", "K19", "X36", "K96", "S97", "T64", "X14", "N38", "Y69", "L41", "H85", "Y39", "R54", "Y29", "T85", "D37", "N98", "W94", "X58", "R84", "R69", "V79", "V17", "B16", "X74", "A24", "J95", "W41", "J98", "H34", "B13", "N74", "Q62", "Y81", "K27", "H27", "E92", "K78", "H81", "D91", "S65", "Z80", "M28", "X16", "M56", "T54", "A42", "H48", "K64", "K50", "G62", "B94", "C46", "H20", "J27", "B64", "H51", "N20", "D86", "R56", "T48", "Q25", "M46", "H29", "C69", "A84", "Q37", "L76", "A63", "V16", "D35", "Q59", "Z27", "T14", "M20", "Y98", "C94", "M58", "D47", "H12", "Y40", "L61", "D52", "B18", "U73", "D59", "G20", "L26", "Z49", "W89", "H42", "L67", "D17", "N39", "C60", "U62", "X86", "R40", "L58", "V49", "H69", "U19", "C43", "V92", "D81", "R29", "U94", "N43", "Z24", "K21", "W37", "H21", "K54", "A98", "D78", "V81", "Z12", "N28", "Y37", "A80", "T32", "Z30", "J52", "Y97", "Q50", "J62", "V12", "T59", "A59", "H28", "K36", "R35", "W90", "S48", "D10", "R73", "X40", "M14", "Y15", "W83", "L68", "J48", "R45", "G70", "A35", "V93", "L17", "E54", "C39", "C89", "L90", "L71", "Z19", "X41", "N25", "S35", "V38", "K91", "R16", "S73", "R10", "R62", "R80", "D27", "G78", "C64", "Q26", "U30", "J15", "L69", "G24", "N91", "L93", "G68", "V27", "P61", "M78", "H64", "S26", "N94", "S49", "G38", "N89", "K98", "L52", "N70", "V86", "D67", "Z39", "L63", "W92", "T31", "T86", "T50", "A73", "X72", "W34", "S43", "P60", "Q28", "X71", "T62", "L27", "V36", "R12", "Z36", "E59", "V60", "D62", "P59", "C27", "W86", "U92", "R70", "Y12", "Y42", "P15", "G72", "Z76", "E63", "B42", "S29", "M21", "N63", "K90", "C57", "U54", "S10", "N96", "M24", "P62", "B27", "K10", "K79", "H49", "U70", "U12", "Z31", "E94", "J60", "V97", "C32", "Q86", "J69", "S31", "K40", "C40", "A34", "Y83", "V15", "C35", "L42", "R79", "J96", "K31", "Y24", "W30", "S39", "R65", "D28", "V61", "C34", "S67", "A50", "L51", "Q91", "A38", "K82", "N16", "J89", "N13", "M74", "K43", "S45", "H84", "X15", "K26", "N27", "G27", "C71", "T94", "F18", "S69", "E76", "G58", "C50", "J17", "B87", "R94", "W20", "D40", "C26", "Q56", "G59", "C80", "J50", "B70", "P71", "P86", "Z72", "T80", "D90", "M65", "S96"]}, {"image": "image_212.jpg", "codechart": "codecharts/code_chart_254.jpg", "codes": ["B86", "S15", "E43", "B95", "B28", "R68", "J45", "U57", "S21", "Q39", "C92", "G92", "H63", "V46", "Q52", "Y72", "K18", "V75", "B96", "C87", "R86", "L39", "B93", "Z57", "W85", "U76", "B30", "E13", "M90", "M72", "R95", "P20", "X78", "Y84", "A28", "P37", "K29", "G69", "D75", "U15", "X67", "W82", "L72", "R18", "U69", "L80", "R34", "W29", "A90", "N68", "U24", "V95", "A78", "D12", "H16", "G23", "Y74", "B79", "Q97", "X82", "Q47", "S58", "N46", "N93", "W87", "Y92", "H15", "L37", "M29", "C25", "J67", "P56", "Y17", "T56", "K75", "P52", "H35", "G95", "H14", "B81", "K20", "T18", "A61", "W70", "T87", "W75", "G93", "Y89", "A19", "X52", "S32", "F45", "A96", "C28", "Q41", "E60", "M40", "X53", "T95", "A48", "C59", "N37", "V72", "U72", "E47", "Z86", "W96", "B54", "Z23", "Z92", "Z63", "X73", "J21", "X28", "X46", "F74", "G71", "A10", "M10", "V19", "M91", "G10", "N71", "Q92", "K19", "Q57", "T10", "Y69", "W81", "N38", "Y56", "S47", "R19", "A83", "H85", "D98", "X12", "F49", "H23", "Y29", "S96", "R61", "W73", "Q32", "P63", "C41", "H40", "U20", "X48", "Z50", "J75", "D63", "Y19", "N80", "X58", "R84", "E97", "Z93", "J43", "V63", "V17", "K89", "J95", "K74", "N74", "B49", "Y81", "K27", "F40", "V73", "T40", "C23", "U85", "T97", "K38", "G62", "A76", "B94", "N17", "P74", "C97", "J27", "H51", "N20", "U48", "C15", "V30", "D96", "P84", "M92", "Z18", "C61", "T90", "N49", "Z75", "S95", "C69", "J61", "A30", "B98", "L76", "T78", "L15", "T24", "X64", "S59", "Q60", "U43", "X37", "D35", "H50", "F90", "M51", "A58", "W61", "U97", "N82", "Y21", "L61", "D52", "P98", "W39", "C20", "L26", "T58", "U16", "X95", "Z25", "L67", "S53", "P26", "V49", "N53", "J40", "B37", "B36", "M42", "V92", "D81", "U94", "N52", "Q17", "C18", "M68", "F38", "E19", "W37", "N24", "M93", "J37", "C53", "D78", "W68", "J49", "G16", "Y27", "M98", "B61", "E96", "Q50", "M76", "H74", "T19", "R35", "M14", "Y15", "V13", "J41", "P45", "L24", "M54", "R71", "S71", "E23", "R45", "Q70", "P21", "Z87", "S30", "V23", "F24", "U13", "F92", "B75", "X41", "X65", "P42", "F54", "A93", "U58", "C63", "P39", "X24", "T79", "Y60", "D27", "J15", "L93", "G68", "V27", "P12", "J46", "S26", "R14", "S49", "Z34", "G38", "H36", "W52", "G64", "F96", "X23", "N70", "K16", "D34", "C58", "D67", "M80", "Y63", "M96", "V41", "T50", "S63", "M13", "R26", "D70", "N65", "F87", "J54", "P68", "V36", "F59", "Y18", "V68", "N35", "F43", "R70", "P90", "P15", "Z76", "A32", "S29", "R67", "C51", "D24", "J92", "N96", "S10", "X54", "Q71", "Q65", "G81", "H49", "Q18", "Q20", "U12", "E94", "K69", "L20", "V97", "M47", "X85", "G50", "J69", "Q86", "K62", "H18", "V78", "M16", "A34", "B24", "K51", "J96", "W97", "Q73", "K60", "D21", "M35", "J56", "Y87", "J29", "R65", "D46", "P40", "V65", "Y54", "L51", "A38", "Q79", "D38", "D42", "M86", "U21", "Q48", "D89", "F51", "S45", "T26", "J70", "G40", "K26", "E93", "X50", "R81", "S62", "K41", "S69", "F68", "G58", "C50", "Q24", "R96", "D40", "C26", "J83", "Q56", "B20", "W28", "B91", "W91", "C80", "P80", "N42", "R87", "K35", "G75", "L23", "N84", "X49", "P23", "J16", "J28"]}, {"image": "image_297.jpg", "codechart": "codecharts/code_chart_255.jpg", "codes": ["D94", "S15", "E43", "B95", "D39", "Y85", "E30", "X56", "J45", "M70", "Z54", "Q93", "H63", "Y79", "Q52", "K83", "A87", "W25", "Z57", "R86", "W85", "Y47", "U76", "P64", "T93", "Q68", "M72", "K15", "R95", "X31", "Z70", "E18", "Y41", "P37", "E70", "S90", "D58", "R52", "D31", "Z81", "M38", "N30", "F69", "H52", "R41", "J90", "L31", "V26", "Z20", "L95", "M62", "Q89", "Z94", "G23", "G18", "P54", "D32", "Y58", "P38", "U61", "V40", "U14", "N46", "L50", "H15", "L45", "G49", "R98", "K45", "N86", "R82", "F12", "S57", "T56", "P52", "K75", "H35", "D50", "Z62", "A69", "U87", "P95", "Q72", "T18", "W70", "T87", "E31", "G93", "N36", "N85", "T89", "U82", "W65", "J38", "G76", "X10", "K68", "X89", "J84", "P30", "G82", "X27", "W47", "F80", "N14", "T95", "X76", "R27", "S68", "S37", "C59", "N62", "U72", "E47", "F26", "Z86", "Z23", "W64", "K28", "C72", "F42", "X73", "A13", "S54", "B90", "X92", "Q53", "X81", "Y94", "U68", "Y14", "L89", "W98", "M10", "L32", "W51", "K48", "J24", "H95", "J93", "K24", "N60", "H76", "T64", "E87", "G32", "Y69", "L41", "S47", "C75", "E15", "P92", "T92", "K95", "T51", "Z41", "H37", "H23", "R61", "E50", "U10", "A45", "X58", "E97", "V63", "V17", "V79", "T68", "X74", "J95", "K74", "F20", "V56", "N76", "P47", "T97", "M56", "X80", "K38", "F28", "X83", "N17", "Y51", "L96", "Y16", "D86", "V90", "M79", "Z18", "Z79", "P72", "C95", "A18", "D73", "F41", "S95", "G21", "G35", "A84", "E24", "B98", "C62", "T39", "Z71", "S59", "Y30", "M15", "P96", "D35", "Q59", "G60", "N58", "Z27", "M52", "K32", "T14", "Z82", "L49", "R58", "U97", "D47", "M84", "T71", "C83", "H67", "G20", "T58", "Z25", "J42", "N39", "R40", "L35", "K37", "J40", "C73", "L46", "Q63", "Z59", "Q17", "F39", "D15", "G86", "K21", "N24", "H21", "J37", "K54", "A98", "H60", "G61", "Z12", "N28", "M98", "K71", "U46", "G48", "M59", "H28", "V62", "W90", "N59", "R73", "X40", "N12", "V13", "L24", "Q96", "L87", "S94", "A35", "Z87", "V87", "S30", "L25", "L71", "U53", "F24", "P42", "P14", "A93", "R16", "C63", "P39", "U84", "S75", "R62", "Y60", "T13", "N83", "B23", "G68", "P61", "G84", "P12", "V35", "S26", "F36", "N94", "P87", "M63", "C49", "K98", "X97", "N70", "D34", "U35", "Z26", "J59", "P41", "B40", "J13", "X17", "T86", "Z83", "V41", "V21", "S63", "L98", "X72", "Z32", "P32", "P60", "L27", "Z90", "X98", "T20", "D62", "J64", "F43", "X90", "Z76", "A32", "R28", "E63", "M21", "K90", "C57", "F86", "U54", "M24", "P62", "R74", "Z97", "B83", "Y76", "Z65", "J80", "F10", "F58", "Q74", "Y50", "M47", "G45", "X85", "V89", "K62", "E53", "U36", "B52", "Y83", "B24", "D30", "C35", "L42", "R64", "R79", "R51", "J35", "Q73", "U56", "D21", "J56", "D64", "G87", "Q14", "L62", "J29", "F70", "D28", "R89", "V65", "Y54", "N67", "E49", "S67", "A50", "L51", "X21", "M43", "W62", "N79", "H26", "D89", "F51", "P57", "D76", "T21", "N73", "F79", "A12", "E98", "V25", "H84", "G40", "J86", "N27", "U91", "K41", "Z60", "Q80", "S69", "E76", "G58", "M85", "P31", "M32", "J17", "K94", "Q56", "G59", "P97", "N72", "L84", "F32", "J78", "W58", "Z72", "T80", "A89", "V94", "J16", "J26"]}, {"image": "image_380.jpg", "codechart": "codecharts/code_chart_256.jpg", "codes": ["E43", "W15", "B28", "B95", "W17", "E30", "Q36", "W76", "Z54", "V82", "N78", "C92", "Z14", "A87", "B96", "D87", "L39", "W85", "P64", "G56", "A81", "A70", "C84", "Z58", "K15", "R95", "F97", "E18", "W71", "D71", "S90", "D58", "U15", "Y36", "R52", "X67", "Y59", "P65", "M87", "V10", "N30", "W45", "N64", "V26", "J71", "L73", "S19", "Y74", "J47", "M64", "K67", "B79", "Y35", "Y58", "X25", "H38", "Z78", "Y45", "X57", "U14", "A41", "Q47", "Y90", "D53", "L75", "R98", "K45", "L37", "E48", "R82", "V83", "T60", "W42", "H35", "D50", "H14", "E39", "M18", "P34", "U26", "K20", "Q72", "T61", "B47", "D26", "P82", "T87", "N36", "D14", "E29", "U82", "J87", "F19", "Z53", "L48", "P78", "Z13", "H83", "X89", "Y68", "T57", "E60", "Q69", "M40", "S80", "X68", "S13", "S68", "S37", "N62", "N10", "R17", "X19", "F26", "F76", "Q10", "F25", "C37", "K42", "U41", "L16", "M10", "K47", "K24", "H61", "N60", "N71", "Q92", "E87", "Q57", "Y69", "L41", "P92", "W54", "Y39", "U32", "R61", "T42", "U10", "C41", "U20", "Q23", "W36", "R84", "Z93", "V17", "G36", "A24", "K74", "K80", "Y81", "V56", "Q27", "V52", "X38", "T28", "D80", "V73", "A62", "D79", "M56", "X80", "K50", "E58", "B94", "C46", "E83", "H20", "P74", "Y16", "R56", "P67", "D96", "W26", "G15", "M92", "G52", "D73", "P10", "H29", "Z75", "Y70", "E67", "S95", "B35", "G21", "N15", "G37", "F47", "A39", "J30", "B98", "L76", "D74", "H31", "Q60", "V16", "W14", "U43", "M15", "Y43", "X37", "G60", "Z27", "M52", "A82", "Z37", "F90", "F73", "L49", "C94", "D47", "L61", "D52", "J31", "C83", "U73", "L26", "Z49", "G19", "T58", "N39", "C60", "R40", "Y82", "S53", "G26", "B50", "P89", "S64", "H69", "L46", "F60", "U19", "F57", "M42", "P43", "Q29", "L30", "N26", "Q49", "C53", "V81", "J49", "D49", "Z30", "J52", "Y78", "T59", "H74", "H28", "K36", "R73", "T49", "X40", "W83", "N12", "C79", "D97", "G43", "S71", "W38", "L87", "T53", "Q70", "H41", "L71", "U13", "F24", "F92", "N19", "S35", "V38", "P91", "U58", "K84", "U84", "C14", "X24", "K93", "T96", "D92", "W18", "L93", "B43", "M78", "F61", "S26", "J36", "Z34", "U96", "H36", "B19", "L52", "V86", "J20", "U35", "W92", "T31", "M96", "Y63", "Z67", "V21", "E78", "M13", "X30", "S43", "W12", "Q28", "Z90", "S85", "X98", "Z36", "U52", "E59", "G91", "V60", "T76", "V68", "V42", "P81", "X90", "B51", "Z91", "G53", "C29", "Y12", "E61", "P15", "B12", "E63", "R76", "S50", "S29", "B42", "K90", "C57", "P29", "P73", "K70", "Q15", "W19", "C42", "U34", "A64", "R74", "K79", "B83", "U12", "Q74", "K69", "F98", "L20", "M47", "A17", "G50", "J69", "Q75", "E53", "V78", "S25", "V15", "W21", "D30", "V39", "R51", "W97", "Q73", "K31", "X51", "E37", "W30", "V67", "G87", "J29", "M31", "E52", "N67", "F75", "M41", "D16", "H53", "B65", "D29", "M30", "A50", "K82", "W63", "N79", "N16", "D42", "E17", "C70", "T38", "S45", "F79", "A12", "E98", "V25", "J70", "W56", "L19", "C71", "R81", "E79", "M89", "S14", "E76", "K81", "M85", "P31", "Q24", "K94", "R37", "J79", "W28", "Y23", "L28", "T63", "F50", "N42", "T83", "K35", "G75", "D41", "B34", "A89", "P85", "B46", "L40", "V94", "J26"]}, {"image": "image_68.jpg", "codechart": "codecharts/code_chart_257.jpg", "codes": ["S15", "M12", "E43", "D39", "P16", "R68", "N41", "X56", "Q36", "A54", "J45", "M70", "S61", "V46", "K83", "M37", "U80", "Z57", "R86", "W85", "Y47", "P64", "B30", "A70", "K15", "P20", "E57", "P37", "D71", "K29", "K46", "D75", "M87", "C31", "R18", "L72", "U17", "A49", "G89", "Z94", "J71", "D93", "Q89", "L73", "B72", "U83", "R25", "T67", "Y45", "Y32", "D18", "U45", "A37", "U67", "D69", "Q30", "N93", "L78", "U65", "T25", "M29", "G13", "K92", "R93", "V83", "T56", "N23", "Q81", "K75", "V59", "R59", "T69", "K39", "B81", "A69", "T74", "E20", "K20", "Q72", "T18", "B47", "P82", "A29", "Q84", "R92", "Q85", "T87", "W70", "C67", "Y89", "W93", "X10", "T36", "P78", "Q54", "S32", "P30", "L54", "Y68", "X27", "W27", "F93", "T57", "H10", "H93", "G83", "S80", "R27", "N10", "A85", "A47", "Z86", "H58", "Q10", "E86", "F89", "R97", "X28", "X46", "U41", "Y48", "L32", "G10", "A79", "F34", "N71", "Q92", "X36", "U49", "N38", "W81", "E35", "S47", "C75", "E15", "F46", "Z16", "P92", "K95", "U71", "Z98", "F49", "D84", "W69", "E50", "N34", "T42", "W73", "R61", "Q32", "P63", "R24", "C41", "D37", "W13", "G65", "Q23", "N69", "J75", "Z50", "V63", "S74", "D13", "H34", "X45", "R48", "H27", "S38", "U50", "K78", "T23", "V73", "X61", "A62", "S60", "M28", "C23", "X16", "T97", "M56", "X80", "T54", "E56", "E26", "L83", "L21", "C21", "E58", "Y51", "L96", "X60", "N20", "R56", "P67", "K97", "D96", "D73", "H29", "T70", "N15", "G35", "V54", "S28", "V47", "S59", "Y30", "V16", "W10", "W14", "A21", "X37", "G60", "Z27", "H50", "M49", "K32", "W84", "D47", "M84", "N82", "D52", "E36", "P98", "F53", "U16", "L67", "Y82", "G26", "P89", "S17", "Q42", "V49", "N53", "S16", "K37", "T46", "C73", "B39", "L46", "Y80", "B36", "N43", "F38", "G86", "Z24", "M93", "J37", "K54", "C53", "Z12", "J49", "D49", "Y27", "U46", "M60", "G25", "T59", "H28", "S48", "T49", "G51", "X40", "M14", "Y15", "K59", "V13", "E74", "P75", "C79", "P58", "J48", "C54", "D97", "W38", "Q70", "P21", "V87", "S30", "L25", "C39", "L90", "Y53", "F92", "X41", "H54", "Y93", "A93", "U58", "A40", "C14", "Z95", "K93", "Y60", "G78", "C64", "J15", "W16", "L69", "N51", "E34", "J74", "Z34", "B19", "G64", "F96", "W57", "V37", "D67", "Z39", "W92", "T31", "M80", "X17", "Z67", "E78", "M13", "X42", "X72", "E71", "N47", "W12", "R78", "N65", "Q28", "B62", "V36", "Z36", "Y18", "A68", "T76", "E65", "G53", "Z76", "A32", "R28", "S50", "G12", "L14", "U54", "K70", "N18", "Q15", "Z64", "M24", "A64", "P62", "Y91", "Z97", "Q65", "G81", "Q18", "Z74", "Q20", "F14", "U12", "K69", "M47", "Z43", "G45", "H90", "G50", "V89", "J69", "S31", "S24", "B52", "A27", "W80", "V15", "B24", "L42", "A65", "F84", "Y24", "K86", "T15", "M31", "S39", "B97", "F15", "D46", "P40", "Y54", "N67", "C34", "Z61", "X21", "M43", "W63", "N79", "E17", "S84", "M86", "H26", "D76", "T26", "B29", "R30", "Z35", "L19", "X15", "G46", "A72", "K41", "E76", "H97", "F68", "K81", "M32", "D25", "W20", "K76", "G59", "B20", "L28", "W74", "R87", "F32", "T83", "S34", "B80", "P71", "P86", "T34", "G75", "A20", "F67", "P85", "M65", "B46", "V94", "S96"]}, {"image": "image_244.jpg", "codechart": "codecharts/code_chart_258.jpg", "codes": ["D95", "B67", "X47", "B28", "R38", "Y85", "Z96", "V82", "Z54", "Q39", "B38", "Y72", "D87", "P64", "H24", "M90", "R95", "T65", "F97", "V28", "X91", "A28", "Y41", "C91", "E41", "U59", "K29", "K46", "V10", "D31", "M87", "U69", "F69", "W29", "B89", "R41", "A43", "L86", "P46", "K72", "M83", "G89", "Z20", "G63", "Q89", "H16", "A56", "N95", "M64", "K67", "B79", "A51", "D20", "A52", "C10", "X57", "W24", "B17", "U67", "L50", "D53", "N93", "G49", "K45", "N86", "C47", "U65", "R15", "K23", "D83", "Y13", "J32", "K92", "J57", "R93", "J67", "S57", "V83", "P52", "V59", "Y49", "M18", "K20", "B47", "D26", "T87", "G57", "X43", "Y46", "J38", "X20", "Y68", "A95", "E32", "H10", "G83", "S37", "V72", "N87", "U72", "Y61", "E47", "X87", "G98", "Z23", "F76", "C38", "A57", "Z92", "S54", "X46", "Y48", "U68", "L32", "G10", "R43", "Q16", "H61", "N97", "G85", "S97", "T64", "Q57", "G32", "Y56", "J25", "S47", "E15", "F46", "M69", "P92", "K95", "U18", "T51", "H23", "D84", "Q31", "R49", "F17", "Q32", "U10", "T85", "B15", "G65", "Z50", "W94", "Y19", "A45", "E97", "K89", "T68", "H34", "K74", "S89", "N74", "B49", "R48", "Q62", "S23", "T29", "U50", "T12", "F94", "H43", "T40", "M28", "W67", "T54", "E56", "E26", "G62", "V69", "R39", "E83", "W78", "Y16", "X60", "U86", "U48", "K97", "G39", "Q25", "P84", "Z18", "G52", "Z79", "S18", "P72", "E67", "F41", "L91", "B35", "B92", "G21", "E40", "T78", "T39", "H31", "Y30", "X37", "G60", "D56", "K32", "M49", "Z37", "F73", "W59", "W23", "N82", "Y21", "A97", "M48", "G19", "T58", "L67", "S53", "B50", "E46", "J40", "T46", "F60", "L46", "C43", "V92", "E84", "Q29", "F91", "Q63", "A36", "N52", "E81", "Q45", "L30", "Q17", "C18", "L29", "A53", "B41", "M68", "G86", "E19", "B84", "G16", "N28", "M60", "M59", "F52", "P49", "W46", "T19", "H28", "R35", "N59", "W90", "T49", "F29", "X40", "E74", "P75", "M61", "S71", "D97", "G70", "W31", "G96", "H68", "C39", "Y53", "E91", "B75", "F92", "N25", "K84", "C63", "S73", "S75", "T79", "R13", "Q64", "G24", "N51", "G68", "M78", "L59", "G30", "R14", "P87", "J19", "R63", "X23", "Y75", "D34", "Z40", "A71", "Z26", "M96", "E78", "M13", "L94", "N47", "K49", "S43", "R78", "F87", "X71", "P68", "L27", "V36", "S41", "X98", "Z36", "Y18", "U52", "E69", "V68", "N35", "J64", "M17", "H56", "B76", "Z52", "E61", "E72", "B42", "S29", "R67", "E63", "G12", "C57", "N90", "D24", "K70", "K56", "S10", "U34", "Z56", "C48", "K10", "K12", "Q65", "Y76", "Z31", "F58", "Q74", "L20", "B85", "G45", "A17", "X85", "H90", "V89", "J69", "H18", "E53", "V78", "S24", "A27", "B58", "C35", "L42", "R64", "R79", "J96", "J35", "W97", "K31", "F84", "M35", "J56", "T15", "V67", "J29", "F70", "D46", "P40", "V65", "C65", "F75", "D68", "M41", "S36", "P25", "S67", "H53", "Z61", "C30", "X21", "F35", "G67", "W62", "M67", "E17", "Q19", "N13", "L43", "P57", "Q46", "F79", "A12", "H84", "W56", "X15", "U23", "X50", "S62", "V43", "Q80", "M50", "H97", "F68", "M32", "Z68", "D57", "J79", "B31", "P97", "C80", "R83", "F50", "P80", "B70", "F32", "P50", "P86", "Z72", "Z73", "D41", "G28", "L40", "U74", "V94", "S96"]}, {"image": "image_310.jpg", "codechart": "codecharts/code_chart_259.jpg", "codes": ["U51", "M12", "S15", "M23", "U40", "E30", "X56", "H63", "Y79", "K83", "Z14", "J94", "T41", "B93", "A15", "U76", "B30", "A70", "J39", "E13", "L34", "T65", "X78", "A28", "E82", "W35", "Y65", "U59", "Q87", "K29", "R52", "M87", "C31", "V34", "W45", "F69", "H52", "J90", "X93", "G94", "M83", "L31", "Z94", "D12", "G23", "H78", "B79", "S51", "Y58", "H38", "P38", "C10", "U61", "Y32", "W24", "D69", "Y90", "E27", "R98", "R15", "J76", "R82", "H47", "J67", "F12", "T56", "N23", "W42", "M18", "K87", "P34", "M73", "Q72", "A29", "N32", "E31", "G57", "G93", "T89", "G14", "Y46", "E28", "J38", "W93", "Y89", "Q54", "B59", "Y67", "E51", "E32", "Q69", "M40", "T82", "G90", "X19", "S12", "H71", "F76", "C38", "A57", "Z63", "Z92", "A13", "S52", "S54", "X46", "B90", "C12", "X81", "U41", "Y94", "Y48", "A10", "F82", "W51", "M91", "A79", "R50", "K48", "Z17", "K19", "X36", "T64", "E87", "T92", "Z21", "X12", "H23", "E73", "Q31", "E50", "R49", "N34", "F95", "F17", "Q32", "P63", "C41", "A92", "D37", "U20", "Y19", "N80", "E97", "V79", "A24", "J95", "W41", "V32", "Q82", "B13", "R48", "Q62", "D72", "H27", "E92", "K78", "T28", "H81", "T27", "K17", "X61", "U28", "D45", "X16", "D65", "H48", "K38", "A76", "Y64", "E58", "F28", "C46", "E83", "N17", "B64", "L53", "Y16", "D86", "U48", "G39", "M79", "H45", "G52", "H70", "A18", "U38", "P10", "H39", "E90", "Z75", "Y70", "A94", "J61", "V54", "J30", "L76", "E40", "H31", "Q60", "Y30", "A63", "G60", "K32", "Z82", "W84", "F90", "F73", "D23", "M51", "A58", "U97", "T71", "N29", "D52", "C83", "G20", "L26", "J42", "Y82", "N53", "Q61", "N61", "P27", "V92", "D81", "R29", "U94", "P53", "A36", "Q17", "C18", "K21", "G41", "H21", "W68", "G61", "Q50", "M60", "G48", "T59", "A59", "W90", "Y38", "P45", "M61", "Q13", "H65", "Q96", "Q35", "P58", "R72", "G43", "J48", "Q70", "R47", "R36", "G96", "H41", "V70", "E91", "M27", "U13", "F92", "N25", "F71", "C63", "P39", "S73", "R10", "V71", "R80", "T13", "G78", "R13", "P24", "W18", "J15", "B23", "L69", "N51", "N91", "N45", "P12", "G84", "C82", "Q90", "F61", "H64", "J36", "F36", "V53", "P87", "M63", "C49", "F65", "K16", "V86", "U29", "Z40", "Z39", "T31", "U78", "J13", "Z83", "C68", "E25", "W34", "Z32", "S43", "D70", "N65", "T62", "B62", "Z90", "C93", "H86", "S41", "F59", "X98", "A68", "E59", "V60", "H46", "V68", "V42", "P81", "C27", "B76", "U42", "Y12", "C29", "Z76", "A32", "N31", "M21", "N63", "G12", "C51", "N18", "Q15", "K56", "J92", "A64", "Y91", "S70", "U70", "F10", "F14", "R60", "Q74", "J60", "E94", "V97", "Y50", "B85", "Z43", "V89", "F13", "C40", "A34", "S92", "B69", "B58", "Y83", "D30", "V39", "R79", "J82", "H32", "X51", "Y24", "A67", "G87", "L62", "F15", "V61", "S91", "D68", "L85", "E49", "C34", "T17", "U64", "A50", "G67", "Q79", "N79", "D42", "S83", "E17", "C70", "Q19", "Q48", "D89", "D76", "P57", "N73", "F79", "V25", "H84", "R30", "W56", "E93", "G46", "G27", "J86", "S62", "E79", "T94", "H97", "P31", "M32", "R94", "C86", "R37", "Q56", "B91", "B31", "P97", "R83", "H17", "B63", "F50", "P80", "F32", "B80", "P86", "Z73", "D90", "M65", "L40"]}, {"image": "image_385.jpg", "codechart": "codecharts/code_chart_260.jpg", "codes": ["B67", "P76", "D95", "W17", "V57", "W76", "Z54", "S21", "V46", "Z14", "P70", "C87", "L39", "B30", "G56", "H24", "C84", "M90", "R95", "F97", "Z70", "G54", "Y41", "E70", "Q87", "D71", "K29", "K63", "X67", "D31", "P65", "W82", "M38", "L72", "N30", "V34", "X79", "R34", "W29", "U24", "L86", "X70", "Q83", "Z20", "J71", "G63", "B72", "G23", "H78", "M64", "J47", "B79", "S51", "V45", "U83", "D20", "A52", "V31", "H38", "Z48", "U61", "V40", "X94", "U14", "Y32", "S58", "A37", "T72", "N46", "D69", "Y90", "D53", "G49", "R98", "K45", "N86", "R15", "D83", "M29", "Y13", "A23", "T56", "N23", "H14", "T74", "U87", "U26", "B47", "D26", "R92", "T87", "Q58", "C67", "D14", "Z29", "G14", "F72", "W93", "F19", "L10", "L79", "X10", "Z13", "X20", "H83", "K68", "X89", "P30", "G82", "D19", "H10", "H93", "X18", "A48", "A85", "U72", "F26", "E47", "B74", "W96", "Z23", "N21", "M95", "Z63", "F42", "E86", "F89", "Z45", "Y94", "A10", "W98", "L32", "W51", "A79", "R43", "F34", "J24", "H61", "Z17", "N60", "H76", "N97", "X36", "G85", "R53", "Z84", "Y69", "C75", "E15", "F46", "P92", "X75", "K95", "U71", "A83", "Z41", "U32", "F49", "D84", "R49", "W73", "U10", "A92", "H40", "W36", "D13", "X35", "J95", "H34", "Y52", "N74", "F20", "R48", "U60", "S23", "N76", "M25", "T12", "K78", "N54", "D80", "X61", "Z80", "T98", "W67", "E26", "K50", "R90", "P13", "H20", "N17", "L53", "H51", "K97", "V90", "V30", "H45", "B14", "H70", "C95", "C61", "P10", "N49", "Z75", "G21", "C78", "G37", "B98", "D74", "Q60", "G60", "M97", "T14", "W84", "C94", "M58", "A58", "W23", "T71", "Y40", "B18", "H67", "H25", "C20", "Z49", "H42", "Z25", "N39", "R40", "Y82", "E46", "X86", "Y26", "Q61", "J40", "Y80", "F57", "P43", "E84", "R29", "A36", "Q45", "L30", "N26", "A53", "F39", "K54", "S76", "T35", "Z12", "J51", "N28", "E75", "T32", "B61", "E96", "H72", "Q50", "F52", "G25", "T59", "M76", "R35", "R73", "X40", "D97", "S94", "Q70", "V87", "S30", "L25", "C39", "M53", "V70", "Z51", "B75", "F92", "X41", "X65", "Y93", "S35", "P14", "U58", "X29", "C63", "V71", "U84", "Z95", "U98", "C14", "V91", "R80", "D27", "G78", "Q64", "N91", "G31", "V27", "H64", "F36", "Y86", "R14", "Z34", "N56", "V24", "F65", "C16", "X23", "V86", "Y75", "U79", "U35", "L63", "J59", "J13", "B21", "Y63", "M96", "T50", "E25", "L98", "E71", "L94", "H96", "V36", "S85", "R12", "A68", "V60", "G91", "H46", "V68", "M57", "P59", "P81", "H56", "E61", "A32", "E63", "C57", "F86", "N90", "K70", "K56", "E10", "N96", "Q71", "R74", "T47", "S70", "Q76", "J80", "U12", "F14", "Z31", "J72", "K69", "E94", "V97", "M47", "C32", "G45", "G50", "B26", "K40", "Q95", "E53", "L38", "L42", "R79", "J35", "H32", "Y24", "E37", "E89", "A67", "G87", "W72", "S42", "F70", "V65", "V64", "V61", "L12", "N67", "T17", "M30", "A50", "Q91", "A38", "S20", "G79", "D42", "J89", "S83", "M67", "H26", "D89", "T38", "T73", "U23", "N27", "S81", "U63", "M89", "F18", "M50", "S69", "F68", "V84", "M32", "K94", "W20", "K76", "J83", "Q56", "R37", "M94", "B31", "L13", "J50", "T63", "B63", "B70", "N42", "R87", "Y62", "P86", "D90", "B34", "L40", "J26"]}]